{
  "generatedAt": "2026-06-08T08:54:20.945Z",
  "region": "eu",
  "cities": [
    "Lymhurst",
    "Martlock",
    "Fort Sterling",
    "Thetford",
    "Bridgewatch",
    "Caerleon",
    "Brecilien"
  ],
  "count": 91,
  "items": [
    {
      "itemId": "T1_CARROT",
      "tier": 1,
      "prices": {
        "Lymhurst": 454,
        "Martlock": 514,
        "Fort Sterling": 484,
        "Thetford": 471,
        "Bridgewatch": 501,
        "Caerleon": 461
      }
    },
    {
      "itemId": "T1_FISHCHOPS",
      "tier": 1,
      "prices": {
        "Lymhurst": 306,
        "Martlock": 327,
        "Fort Sterling": 302,
        "Thetford": 288,
        "Bridgewatch": 304,
        "Caerleon": 328,
        "Brecilien": 345
      }
    },
    {
      "itemId": "T1_SEAWEED",
      "tier": 1,
      "prices": {
        "Lymhurst": 360,
        "Martlock": 305,
        "Fort Sterling": 347,
        "Thetford": 300,
        "Bridgewatch": 389,
        "Caerleon": 747,
        "Brecilien": 401
      }
    },
    {
      "itemId": "T2_AGARIC",
      "tier": 2,
      "prices": {
        "Lymhurst": 477,
        "Martlock": 510,
        "Thetford": 463,
        "Brecilien": 479
      }
    },
    {
      "itemId": "T2_BEAN",
      "tier": 2,
      "prices": {
        "Lymhurst": 464,
        "Martlock": 549,
        "Bridgewatch": 472
      }
    },
    {
      "itemId": "T3_COMFREY",
      "tier": 3,
      "prices": {
        "Lymhurst": 506,
        "Martlock": 507,
        "Fort Sterling": 502,
        "Thetford": 510,
        "Bridgewatch": 497,
        "Brecilien": 538
      }
    },
    {
      "itemId": "T3_FARM_CHICKEN_GROWN",
      "tier": 3,
      "prices": {
        "Lymhurst": 9000,
        "Bridgewatch": 9394
      }
    },
    {
      "itemId": "T3_FLOUR",
      "tier": 3,
      "prices": {
        "Lymhurst": 534,
        "Martlock": 530,
        "Fort Sterling": 570,
        "Bridgewatch": 541,
        "Brecilien": 893
      }
    },
    {
      "itemId": "T3_FISH_FRESHWATER_SWAMP_RARE",
      "tier": 3,
      "prices": {
        "Martlock": 2553,
        "Fort Sterling": 2871,
        "Thetford": 2500,
        "Bridgewatch": 2999,
        "Caerleon": 2376
      }
    },
    {
      "itemId": "T3_FISH_FRESHWATER_FOREST_RARE",
      "tier": 3,
      "prices": {
        "Lymhurst": 2924,
        "Martlock": 2541,
        "Fort Sterling": 2884,
        "Thetford": 2549,
        "Bridgewatch": 2638,
        "Caerleon": 2458,
        "Brecilien": 2994
      }
    },
    {
      "itemId": "T3_EGG",
      "tier": 3,
      "prices": {
        "Lymhurst": 139,
        "Martlock": 80,
        "Fort Sterling": 67,
        "Thetford": 312,
        "Caerleon": 150,
        "Brecilien": 157
      }
    },
    {
      "itemId": "T3_FISH_FRESHWATER_STEPPE_RARE",
      "tier": 3,
      "prices": {
        "Lymhurst": 2726,
        "Martlock": 2571,
        "Fort Sterling": 2722,
        "Thetford": 2548,
        "Bridgewatch": 2645,
        "Brecilien": 3391
      }
    },
    {
      "itemId": "T3_MEAT",
      "tier": 3,
      "prices": {
        "Lymhurst": 514,
        "Martlock": 788,
        "Fort Sterling": 472,
        "Thetford": 492,
        "Bridgewatch": 486
      }
    },
    {
      "itemId": "T3_ALCHEMY_RARE_EAGLE",
      "tier": 3,
      "prices": {
        "Lymhurst": 22992,
        "Martlock": 11400,
        "Fort Sterling": 14989,
        "Thetford": 29983,
        "Bridgewatch": 14885,
        "Caerleon": 13828,
        "Brecilien": 16371
      }
    },
    {
      "itemId": "T3_ALCHEMY_RARE_IMP",
      "tier": 3,
      "prices": {
        "Lymhurst": 29777,
        "Martlock": 24568,
        "Thetford": 16992,
        "Caerleon": 28988,
        "Brecilien": 19997
      }
    },
    {
      "itemId": "T3_ALCHEMY_RARE_ELEMENTAL",
      "tier": 3,
      "prices": {
        "Lymhurst": 10998,
        "Martlock": 13999,
        "Thetford": 14991,
        "Brecilien": 12490
      }
    },
    {
      "itemId": "T3_ALCHEMY_RARE_PANTHER",
      "tier": 3,
      "prices": {
        "Lymhurst": 81930,
        "Martlock": 59000,
        "Thetford": 76989,
        "Bridgewatch": 65646,
        "Caerleon": 79983,
        "Brecilien": 59984
      }
    },
    {
      "itemId": "T3_ALCHEMY_RARE_DIREBEAR",
      "tier": 3,
      "prices": {
        "Lymhurst": 27643,
        "Fort Sterling": 23907,
        "Caerleon": 49977,
        "Brecilien": 24990
      }
    },
    {
      "itemId": "T3_ALCHEMY_RARE_ENT",
      "tier": 3,
      "prices": {
        "Fort Sterling": 21982,
        "Thetford": 15999,
        "Caerleon": 34968
      }
    },
    {
      "itemId": "T3_ALCHEMY_RARE_WEREWOLF",
      "tier": 3,
      "prices": {
        "Lymhurst": 13978,
        "Martlock": 15110,
        "Fort Sterling": 12800,
        "Bridgewatch": 18499
      }
    },
    {
      "itemId": "T3_FISH_SALTWATER_ALL_RARE",
      "tier": 3,
      "prices": {
        "Lymhurst": 2889,
        "Martlock": 2952,
        "Fort Sterling": 2883,
        "Thetford": 2573,
        "Bridgewatch": 2641
      }
    },
    {
      "itemId": "T3_WHEAT",
      "tier": 3,
      "prices": {
        "Lymhurst": 537,
        "Martlock": 515,
        "Fort Sterling": 519,
        "Thetford": 539,
        "Bridgewatch": 528,
        "Brecilien": 760
      }
    },
    {
      "itemId": "T3_FISH_FRESHWATER_HIGHLANDS_RARE",
      "tier": 3,
      "prices": {
        "Lymhurst": 2927,
        "Martlock": 2531,
        "Fort Sterling": 2879,
        "Bridgewatch": 2640,
        "Caerleon": 2573
      }
    },
    {
      "itemId": "T3_FISH_FRESHWATER_MOUNTAIN_RARE",
      "tier": 3,
      "prices": {
        "Martlock": 2664,
        "Fort Sterling": 2874,
        "Bridgewatch": 2641
      }
    },
    {
      "itemId": "T3_FISH_FRESHWATER_AVALON_RARE",
      "tier": 3,
      "prices": {
        "Lymhurst": 2850,
        "Martlock": 2561,
        "Fort Sterling": 2872,
        "Thetford": 2546,
        "Bridgewatch": 3647,
        "Brecilien": 2860
      }
    },
    {
      "itemId": "T4_BREAD",
      "tier": 4,
      "prices": {
        "Lymhurst": 506,
        "Martlock": 413,
        "Fort Sterling": 498,
        "Bridgewatch": 477,
        "Caerleon": 300,
        "Brecilien": 552
      }
    },
    {
      "itemId": "T4_BURDOCK",
      "tier": 4,
      "prices": {
        "Lymhurst": 513,
        "Martlock": 521,
        "Fort Sterling": 472,
        "Thetford": 548,
        "Bridgewatch": 474,
        "Brecilien": 510
      }
    },
    {
      "itemId": "T4_FARM_GOAT_GROWN",
      "tier": 4,
      "prices": {
        "Lymhurst": 9999,
        "Fort Sterling": 9882,
        "Bridgewatch": 10156
      }
    },
    {
      "itemId": "T4_BUTTER",
      "tier": 4,
      "prices": {
        "Lymhurst": 206,
        "Martlock": 177,
        "Fort Sterling": 193,
        "Bridgewatch": 229,
        "Caerleon": 258,
        "Brecilien": 317
      }
    },
    {
      "itemId": "T4_MILK",
      "tier": 4,
      "prices": {
        "Lymhurst": 315,
        "Martlock": 332,
        "Fort Sterling": 294,
        "Bridgewatch": 295,
        "Brecilien": 443
      }
    },
    {
      "itemId": "T4_MEAT",
      "tier": 4,
      "prices": {
        "Lymhurst": 506,
        "Martlock": 497,
        "Thetford": 503,
        "Bridgewatch": 486
      }
    },
    {
      "itemId": "T4_TURNIP",
      "tier": 4,
      "prices": {
        "Lymhurst": 474,
        "Martlock": 519,
        "Fort Sterling": 435,
        "Bridgewatch": 504
      }
    },
    {
      "itemId": "T5_CABBAGE",
      "tier": 5,
      "prices": {
        "Lymhurst": 529,
        "Martlock": 540,
        "Fort Sterling": 593,
        "Thetford": 460,
        "Bridgewatch": 489,
        "Brecilien": 490
      }
    },
    {
      "itemId": "T5_FISH_FRESHWATER_AVALON_RARE",
      "tier": 5,
      "prices": {
        "Lymhurst": 5788,
        "Martlock": 5981,
        "Fort Sterling": 5335,
        "Thetford": 5064,
        "Bridgewatch": 5444,
        "Brecilien": 5681
      }
    },
    {
      "itemId": "T5_TEASEL",
      "tier": 5,
      "prices": {
        "Lymhurst": 499,
        "Martlock": 505,
        "Fort Sterling": 486,
        "Thetford": 534,
        "Bridgewatch": 468,
        "Caerleon": 428,
        "Brecilien": 486
      }
    },
    {
      "itemId": "T5_FISH_FRESHWATER_STEPPE_RARE",
      "tier": 5,
      "prices": {
        "Martlock": 5749,
        "Fort Sterling": 5398,
        "Thetford": 5594,
        "Bridgewatch": 5431,
        "Caerleon": 5197
      }
    },
    {
      "itemId": "T5_ALCHEMY_RARE_EAGLE",
      "tier": 5,
      "prices": {
        "Lymhurst": 23993,
        "Fort Sterling": 18983,
        "Brecilien": 21984
      }
    },
    {
      "itemId": "T5_ALCHEMY_RARE_IMP",
      "tier": 5,
      "prices": {
        "Lymhurst": 33976,
        "Fort Sterling": 30972,
        "Brecilien": 27992
      }
    },
    {
      "itemId": "T5_ALCHEMY_RARE_ELEMENTAL",
      "tier": 5,
      "prices": {
        "Lymhurst": 23412,
        "Martlock": 19998,
        "Thetford": 29986,
        "Bridgewatch": 39987,
        "Brecilien": 21913
      }
    },
    {
      "itemId": "T5_ALCHEMY_RARE_PANTHER",
      "tier": 5,
      "prices": {
        "Lymhurst": 114984,
        "Fort Sterling": 109995,
        "Thetford": 113993,
        "Caerleon": 129995,
        "Brecilien": 103698
      }
    },
    {
      "itemId": "T5_ALCHEMY_RARE_DIREBEAR",
      "tier": 5,
      "prices": {
        "Lymhurst": 42991,
        "Martlock": 37997,
        "Fort Sterling": 46456,
        "Thetford": 42999,
        "Caerleon": 64999,
        "Brecilien": 42996
      }
    },
    {
      "itemId": "T5_ALCHEMY_RARE_ENT",
      "tier": 5,
      "prices": {
        "Lymhurst": 42895,
        "Martlock": 38996,
        "Fort Sterling": 44976,
        "Thetford": 38997,
        "Caerleon": 60908,
        "Brecilien": 42467
      }
    },
    {
      "itemId": "T5_ALCHEMY_RARE_WEREWOLF",
      "tier": 5,
      "prices": {
        "Lymhurst": 21968,
        "Martlock": 20000,
        "Fort Sterling": 24411,
        "Thetford": 26998,
        "Brecilien": 28994
      }
    },
    {
      "itemId": "T5_FARM_GOOSE_GROWN",
      "tier": 5,
      "prices": {
        "Lymhurst": 9992,
        "Bridgewatch": 11483
      }
    },
    {
      "itemId": "T5_EGG",
      "tier": 5,
      "prices": {
        "Lymhurst": 345,
        "Martlock": 378,
        "Thetford": 379,
        "Bridgewatch": 403,
        "Caerleon": 457,
        "Brecilien": 416
      }
    },
    {
      "itemId": "T5_FISH_SALTWATER_ALL_RARE",
      "tier": 5,
      "prices": {
        "Martlock": 5165,
        "Fort Sterling": 6097,
        "Bridgewatch": 5197
      }
    },
    {
      "itemId": "T5_FISH_FRESHWATER_MOUNTAIN_RARE",
      "tier": 5,
      "prices": {
        "Martlock": 5595,
        "Fort Sterling": 5963,
        "Thetford": 6044
      }
    },
    {
      "itemId": "T5_FISH_FRESHWATER_SWAMP_RARE",
      "tier": 5,
      "prices": {
        "Lymhurst": 5938,
        "Martlock": 5677,
        "Fort Sterling": 5645,
        "Thetford": 4799,
        "Caerleon": 5634
      }
    },
    {
      "itemId": "T5_MEAT",
      "tier": 5,
      "prices": {
        "Lymhurst": 514,
        "Martlock": 490,
        "Fort Sterling": 488,
        "Thetford": 500,
        "Bridgewatch": 501
      }
    },
    {
      "itemId": "T5_FISH_FRESHWATER_FOREST_RARE",
      "tier": 5,
      "prices": {
        "Martlock": 6000,
        "Bridgewatch": 6500,
        "Caerleon": 6000,
        "Brecilien": 7843
      }
    },
    {
      "itemId": "T5_FISH_FRESHWATER_HIGHLANDS_RARE",
      "tier": 5,
      "prices": {
        "Martlock": 5436,
        "Fort Sterling": 5795,
        "Thetford": 5655,
        "Bridgewatch": 5697,
        "Brecilien": 6096
      }
    },
    {
      "itemId": "QUESTITEM_TOKEN_AVALON",
      "tier": 0,
      "prices": {
        "Lymhurst": 2185,
        "Martlock": 2214,
        "Fort Sterling": 2213,
        "Thetford": 2266,
        "Bridgewatch": 2329,
        "Caerleon": 3093,
        "Brecilien": 2177
      }
    },
    {
      "itemId": "T6_FOXGLOVE",
      "tier": 6,
      "prices": {
        "Lymhurst": 544,
        "Martlock": 488,
        "Fort Sterling": 525,
        "Thetford": 518,
        "Bridgewatch": 501,
        "Caerleon": 515,
        "Brecilien": 555
      }
    },
    {
      "itemId": "T6_ALCOHOL",
      "tier": 6,
      "prices": {
        "Lymhurst": 563,
        "Martlock": 443,
        "Fort Sterling": 446,
        "Thetford": 562,
        "Bridgewatch": 540,
        "Caerleon": 425,
        "Brecilien": 414
      }
    },
    {
      "itemId": "T6_POTATO",
      "tier": 6,
      "prices": {
        "Lymhurst": 536,
        "Martlock": 510,
        "Fort Sterling": 665,
        "Thetford": 544,
        "Bridgewatch": 533,
        "Caerleon": 595,
        "Brecilien": 540
      }
    },
    {
      "itemId": "T6_MEAT",
      "tier": 6,
      "prices": {
        "Lymhurst": 510,
        "Martlock": 503,
        "Fort Sterling": 481,
        "Thetford": 502,
        "Bridgewatch": 543,
        "Brecilien": 587
      }
    },
    {
      "itemId": "T6_FARM_SHEEP_GROWN",
      "tier": 6,
      "prices": {
        "Lymhurst": 9397,
        "Martlock": 10298,
        "Bridgewatch": 12247
      }
    },
    {
      "itemId": "T6_BUTTER",
      "tier": 6,
      "prices": {
        "Lymhurst": 582,
        "Martlock": 545,
        "Bridgewatch": 520,
        "Caerleon": 537,
        "Brecilien": 601
      }
    },
    {
      "itemId": "T6_MILK",
      "tier": 6,
      "prices": {
        "Lymhurst": 491,
        "Martlock": 481,
        "Fort Sterling": 451,
        "Thetford": 495,
        "Bridgewatch": 465,
        "Caerleon": 599,
        "Brecilien": 693
      }
    },
    {
      "itemId": "T7_FISH_FRESHWATER_SWAMP_RARE",
      "tier": 7,
      "prices": {
        "Lymhurst": 9382,
        "Martlock": 7986,
        "Fort Sterling": 8752,
        "Thetford": 8443,
        "Bridgewatch": 9187,
        "Caerleon": 13997,
        "Brecilien": 8498
      }
    },
    {
      "itemId": "T7_CORN",
      "tier": 7,
      "prices": {
        "Lymhurst": 528,
        "Martlock": 515,
        "Fort Sterling": 485,
        "Thetford": 567,
        "Bridgewatch": 484,
        "Caerleon": 550,
        "Brecilien": 499
      }
    },
    {
      "itemId": "T7_ALCOHOL",
      "tier": 7,
      "prices": {
        "Lymhurst": 562,
        "Martlock": 479,
        "Fort Sterling": 523,
        "Bridgewatch": 527,
        "Caerleon": 412,
        "Brecilien": 438
      }
    },
    {
      "itemId": "T7_FISH_FRESHWATER_FOREST_RARE",
      "tier": 7,
      "prices": {
        "Lymhurst": 127499,
        "Martlock": 128999,
        "Fort Sterling": 126647,
        "Thetford": 127932,
        "Bridgewatch": 130679,
        "Caerleon": 130000,
        "Brecilien": 138880
      }
    },
    {
      "itemId": "T7_FISH_SALTWATER_ALL_RARE",
      "tier": 7,
      "prices": {
        "Lymhurst": 50794,
        "Martlock": 55953,
        "Fort Sterling": 53997,
        "Thetford": 48966,
        "Bridgewatch": 53990,
        "Caerleon": 59978,
        "Brecilien": 43995
      }
    },
    {
      "itemId": "T7_FISH_FRESHWATER_STEPPE_RARE",
      "tier": 7,
      "prices": {
        "Lymhurst": 8967,
        "Martlock": 8963,
        "Fort Sterling": 9460,
        "Thetford": 9984,
        "Bridgewatch": 9251,
        "Caerleon": 12949,
        "Brecilien": 9994
      }
    },
    {
      "itemId": "T7_ALCHEMY_RARE_EAGLE",
      "tier": 7,
      "prices": {
        "Lymhurst": 85960,
        "Martlock": 89997,
        "Thetford": 52993,
        "Bridgewatch": 65000,
        "Caerleon": 90000,
        "Brecilien": 56587
      }
    },
    {
      "itemId": "T7_ALCHEMY_RARE_IMP",
      "tier": 7,
      "prices": {
        "Lymhurst": 199991,
        "Martlock": 192485,
        "Thetford": 165000,
        "Bridgewatch": 199945,
        "Caerleon": 199999,
        "Brecilien": 179991
      }
    },
    {
      "itemId": "T7_ALCHEMY_RARE_ELEMENTAL",
      "tier": 7,
      "prices": {
        "Martlock": 84996,
        "Thetford": 53987,
        "Bridgewatch": 59967,
        "Caerleon": 79995,
        "Brecilien": 56966
      }
    },
    {
      "itemId": "T7_ALCHEMY_RARE_PANTHER",
      "tier": 7,
      "prices": {
        "Lymhurst": 209997,
        "Martlock": 217498,
        "Fort Sterling": 216454,
        "Thetford": 221996,
        "Bridgewatch": 234907,
        "Caerleon": 279961,
        "Brecilien": 217994
      }
    },
    {
      "itemId": "T7_ALCHEMY_RARE_DIREBEAR",
      "tier": 7,
      "prices": {
        "Lymhurst": 99988,
        "Martlock": 185999,
        "Fort Sterling": 98963,
        "Caerleon": 189951,
        "Brecilien": 90031
      }
    },
    {
      "itemId": "T7_ALCHEMY_RARE_ENT",
      "tier": 7,
      "prices": {
        "Martlock": 179997,
        "Fort Sterling": 249896,
        "Caerleon": 222221,
        "Brecilien": 219000
      }
    },
    {
      "itemId": "T7_ALCHEMY_RARE_WEREWOLF",
      "tier": 7,
      "prices": {
        "Lymhurst": 54988,
        "Martlock": 55459,
        "Fort Sterling": 86982,
        "Thetford": 71993,
        "Brecilien": 57765
      }
    },
    {
      "itemId": "T7_MULLEIN",
      "tier": 7,
      "prices": {
        "Lymhurst": 597,
        "Martlock": 550,
        "Fort Sterling": 594,
        "Thetford": 546,
        "Bridgewatch": 580,
        "Caerleon": 474,
        "Brecilien": 648
      }
    },
    {
      "itemId": "T7_FISH_FRESHWATER_MOUNTAIN_RARE",
      "tier": 7,
      "prices": {
        "Lymhurst": 9954,
        "Martlock": 10912,
        "Fort Sterling": 8894,
        "Thetford": 8954,
        "Bridgewatch": 9888,
        "Brecilien": 11981
      }
    },
    {
      "itemId": "T7_FARM_PIG_GROWN",
      "tier": 7,
      "prices": {
        "Lymhurst": 11177,
        "Martlock": 11694,
        "Thetford": 10991,
        "Bridgewatch": 11049,
        "Caerleon": 10500,
        "Brecilien": 11555
      }
    },
    {
      "itemId": "T7_FISH_FRESHWATER_AVALON_RARE",
      "tier": 7,
      "prices": {
        "Lymhurst": 98982,
        "Martlock": 98885,
        "Fort Sterling": 124936,
        "Thetford": 85443,
        "Bridgewatch": 88879,
        "Caerleon": 122984,
        "Brecilien": 95967
      }
    },
    {
      "itemId": "T7_MEAT",
      "tier": 7,
      "prices": {
        "Lymhurst": 529,
        "Martlock": 589,
        "Fort Sterling": 519,
        "Thetford": 507,
        "Bridgewatch": 508,
        "Caerleon": 492,
        "Brecilien": 558
      }
    },
    {
      "itemId": "T7_FISH_FRESHWATER_HIGHLANDS_RARE",
      "tier": 7,
      "prices": {
        "Lymhurst": 12984,
        "Martlock": 14982,
        "Thetford": 13954,
        "Bridgewatch": 13000,
        "Caerleon": 14998,
        "Brecilien": 19179
      }
    },
    {
      "itemId": "T8_FARM_COW_GROWN",
      "tier": 8,
      "prices": {
        "Lymhurst": 9999,
        "Martlock": 11290,
        "Bridgewatch": 10490,
        "Caerleon": 18770,
        "Brecilien": 12889
      }
    },
    {
      "itemId": "T8_BUTTER",
      "tier": 8,
      "prices": {
        "Lymhurst": 509,
        "Martlock": 553,
        "Thetford": 494,
        "Bridgewatch": 484,
        "Caerleon": 429,
        "Brecilien": 675
      }
    },
    {
      "itemId": "T8_MILK",
      "tier": 8,
      "prices": {
        "Lymhurst": 433,
        "Martlock": 419,
        "Fort Sterling": 458,
        "Thetford": 455,
        "Bridgewatch": 453,
        "Caerleon": 550,
        "Brecilien": 506
      }
    },
    {
      "itemId": "T8_YARROW",
      "tier": 8,
      "prices": {
        "Lymhurst": 543,
        "Martlock": 519,
        "Fort Sterling": 509,
        "Thetford": 531,
        "Bridgewatch": 563,
        "Caerleon": 481,
        "Brecilien": 524
      }
    },
    {
      "itemId": "T8_PUMPKIN",
      "tier": 8,
      "prices": {
        "Lymhurst": 460,
        "Martlock": 599,
        "Fort Sterling": 505,
        "Thetford": 538,
        "Bridgewatch": 522,
        "Caerleon": 553,
        "Brecilien": 506
      }
    },
    {
      "itemId": "T8_ALCOHOL",
      "tier": 8,
      "prices": {
        "Lymhurst": 467,
        "Martlock": 485,
        "Thetford": 441,
        "Caerleon": 414,
        "Brecilien": 482
      }
    },
    {
      "itemId": "T8_MEAT",
      "tier": 8,
      "prices": {
        "Lymhurst": 509,
        "Martlock": 501,
        "Fort Sterling": 584,
        "Thetford": 539,
        "Bridgewatch": 584,
        "Caerleon": 526,
        "Brecilien": 564
      }
    },
    {
      "itemId": "T1_FISHSAUCE_LEVEL1",
      "tier": 1,
      "prices": {
        "Lymhurst": 4995,
        "Martlock": 4696,
        "Fort Sterling": 4275,
        "Thetford": 4848,
        "Caerleon": 6077,
        "Brecilien": 4948
      }
    },
    {
      "itemId": "T1_FISHSAUCE_LEVEL2",
      "tier": 1,
      "prices": {
        "Martlock": 14982,
        "Thetford": 15400,
        "Caerleon": 14999,
        "Brecilien": 15556
      }
    },
    {
      "itemId": "T1_FISHSAUCE_LEVEL3",
      "tier": 1,
      "prices": {
        "Martlock": 44791,
        "Caerleon": 44984
      }
    },
    {
      "itemId": "T1_ALCHEMY_EXTRACT_LEVEL1",
      "tier": 1,
      "prices": {
        "Caerleon": 5609,
        "Brecilien": 3113
      }
    },
    {
      "itemId": "T1_ALCHEMY_EXTRACT_LEVEL2",
      "tier": 1,
      "prices": {}
    },
    {
      "itemId": "T1_ALCHEMY_EXTRACT_LEVEL3",
      "tier": 1,
      "prices": {
        "Martlock": 23985
      }
    }
  ]
}