{
  "generatedAt": "2026-05-21T12:54:39.392Z",
  "region": "us",
  "cities": [
    "Lymhurst",
    "Martlock",
    "Fort Sterling",
    "Thetford",
    "Bridgewatch",
    "Caerleon",
    "Brecilien"
  ],
  "count": 105,
  "items": [
    {
      "itemId": "T4_METALBAR",
      "tier": 4,
      "enchant": 0,
      "prices": {
        "Lymhurst": 342,
        "Martlock": 306,
        "Fort Sterling": 260,
        "Thetford": 288,
        "Bridgewatch": 295,
        "Caerleon": 459,
        "Brecilien": 291
      }
    },
    {
      "itemId": "T4_METALBAR_LEVEL1@1",
      "tier": 4,
      "enchant": 1,
      "prices": {
        "Lymhurst": 748,
        "Martlock": 0,
        "Fort Sterling": 606,
        "Thetford": 542,
        "Bridgewatch": 1193,
        "Caerleon": 745,
        "Brecilien": 0
      }
    },
    {
      "itemId": "T4_METALBAR_LEVEL2@2",
      "tier": 4,
      "enchant": 2,
      "prices": {
        "Lymhurst": 2458,
        "Martlock": 2099,
        "Fort Sterling": 2181,
        "Thetford": 1973,
        "Bridgewatch": 2177,
        "Caerleon": 2881,
        "Brecilien": 0
      }
    },
    {
      "itemId": "T4_METALBAR_LEVEL3@3",
      "tier": 4,
      "enchant": 3,
      "prices": {
        "Lymhurst": 7999,
        "Martlock": 7497,
        "Fort Sterling": 7694,
        "Thetford": 6718,
        "Bridgewatch": 7800,
        "Caerleon": 7916,
        "Brecilien": 0
      }
    },
    {
      "itemId": "T4_METALBAR_LEVEL4@4",
      "tier": 4,
      "enchant": 4,
      "prices": {
        "Lymhurst": 41802,
        "Martlock": 42376,
        "Fort Sterling": 44958,
        "Thetford": 38998,
        "Bridgewatch": 42383,
        "Caerleon": 49980,
        "Brecilien": 45999
      }
    },
    {
      "itemId": "T5_METALBAR",
      "tier": 5,
      "enchant": 0,
      "prices": {
        "Lymhurst": 999,
        "Martlock": 0,
        "Fort Sterling": 976,
        "Thetford": 849,
        "Bridgewatch": 1089,
        "Caerleon": 989,
        "Brecilien": 0
      }
    },
    {
      "itemId": "T5_METALBAR_LEVEL1@1",
      "tier": 5,
      "enchant": 1,
      "prices": {
        "Lymhurst": 1732,
        "Martlock": 1814,
        "Fort Sterling": 1647,
        "Thetford": 0,
        "Bridgewatch": 1797,
        "Caerleon": 0,
        "Brecilien": 0
      }
    },
    {
      "itemId": "T5_METALBAR_LEVEL2@2",
      "tier": 5,
      "enchant": 2,
      "prices": {
        "Lymhurst": 7280,
        "Martlock": 0,
        "Fort Sterling": 6248,
        "Thetford": 0,
        "Bridgewatch": 6400,
        "Caerleon": 6825,
        "Brecilien": 0
      }
    },
    {
      "itemId": "T5_METALBAR_LEVEL3@3",
      "tier": 5,
      "enchant": 3,
      "prices": {
        "Lymhurst": 28781,
        "Martlock": 28392,
        "Fort Sterling": 26996,
        "Thetford": 0,
        "Bridgewatch": 28634,
        "Caerleon": 27795,
        "Brecilien": 0
      }
    },
    {
      "itemId": "T5_METALBAR_LEVEL4@4",
      "tier": 5,
      "enchant": 4,
      "prices": {
        "Lymhurst": 124967,
        "Martlock": 116997,
        "Fort Sterling": 113185,
        "Thetford": 0,
        "Bridgewatch": 117896,
        "Caerleon": 137999,
        "Brecilien": 0
      }
    },
    {
      "itemId": "T6_METALBAR",
      "tier": 6,
      "enchant": 0,
      "prices": {
        "Lymhurst": 3178,
        "Martlock": 0,
        "Fort Sterling": 2891,
        "Thetford": 2940,
        "Bridgewatch": 3111,
        "Caerleon": 3495,
        "Brecilien": 0
      }
    },
    {
      "itemId": "T6_METALBAR_LEVEL1@1",
      "tier": 6,
      "enchant": 1,
      "prices": {
        "Lymhurst": 8100,
        "Martlock": 0,
        "Fort Sterling": 6500,
        "Thetford": 6789,
        "Bridgewatch": 7231,
        "Caerleon": 7357,
        "Brecilien": 0
      }
    },
    {
      "itemId": "T6_METALBAR_LEVEL2@2",
      "tier": 6,
      "enchant": 2,
      "prices": {
        "Lymhurst": 26979,
        "Martlock": 0,
        "Fort Sterling": 27488,
        "Thetford": 28740,
        "Bridgewatch": 26989,
        "Caerleon": 26999,
        "Brecilien": 0
      }
    },
    {
      "itemId": "T6_METALBAR_LEVEL3@3",
      "tier": 6,
      "enchant": 3,
      "prices": {
        "Lymhurst": 97202,
        "Martlock": 109987,
        "Fort Sterling": 92992,
        "Thetford": 89498,
        "Bridgewatch": 95498,
        "Caerleon": 96500,
        "Brecilien": 0
      }
    },
    {
      "itemId": "T6_METALBAR_LEVEL4@4",
      "tier": 6,
      "enchant": 4,
      "prices": {
        "Lymhurst": 399996,
        "Martlock": 340000,
        "Fort Sterling": 355486,
        "Thetford": 339995,
        "Bridgewatch": 359995,
        "Caerleon": 367000,
        "Brecilien": 0
      }
    },
    {
      "itemId": "T7_METALBAR",
      "tier": 7,
      "enchant": 0,
      "prices": {
        "Lymhurst": 7898,
        "Martlock": 7882,
        "Fort Sterling": 7526,
        "Thetford": 7710,
        "Bridgewatch": 7996,
        "Caerleon": 8646,
        "Brecilien": 0
      }
    },
    {
      "itemId": "T7_METALBAR_LEVEL1@1",
      "tier": 7,
      "enchant": 1,
      "prices": {
        "Lymhurst": 25497,
        "Martlock": 0,
        "Fort Sterling": 24987,
        "Thetford": 24887,
        "Bridgewatch": 25989,
        "Caerleon": 27491,
        "Brecilien": 0
      }
    },
    {
      "itemId": "T7_METALBAR_LEVEL2@2",
      "tier": 7,
      "enchant": 2,
      "prices": {
        "Lymhurst": 86993,
        "Martlock": 82885,
        "Fort Sterling": 88996,
        "Thetford": 77689,
        "Bridgewatch": 89451,
        "Caerleon": 96498,
        "Brecilien": 0
      }
    },
    {
      "itemId": "T7_METALBAR_LEVEL3@3",
      "tier": 7,
      "enchant": 3,
      "prices": {
        "Lymhurst": 265000,
        "Martlock": 254982,
        "Fort Sterling": 260993,
        "Thetford": 242000,
        "Bridgewatch": 258990,
        "Caerleon": 230000,
        "Brecilien": 0
      }
    },
    {
      "itemId": "T7_METALBAR_LEVEL4@4",
      "tier": 7,
      "enchant": 4,
      "prices": {
        "Lymhurst": 0,
        "Martlock": 0,
        "Fort Sterling": 1399999,
        "Thetford": 1279996,
        "Bridgewatch": 1654538,
        "Caerleon": 0,
        "Brecilien": 0
      }
    },
    {
      "itemId": "T8_METALBAR",
      "tier": 8,
      "enchant": 0,
      "prices": {
        "Lymhurst": 28986,
        "Martlock": 28985,
        "Fort Sterling": 28495,
        "Thetford": 27895,
        "Bridgewatch": 30965,
        "Caerleon": 39493,
        "Brecilien": 0
      }
    },
    {
      "itemId": "T8_METALBAR_LEVEL1@1",
      "tier": 8,
      "enchant": 1,
      "prices": {
        "Lymhurst": 89996,
        "Martlock": 83990,
        "Fort Sterling": 82988,
        "Thetford": 83495,
        "Bridgewatch": 93995,
        "Caerleon": 88985,
        "Brecilien": 0
      }
    },
    {
      "itemId": "T8_METALBAR_LEVEL2@2",
      "tier": 8,
      "enchant": 2,
      "prices": {
        "Lymhurst": 242117,
        "Martlock": 243986,
        "Fort Sterling": 258998,
        "Thetford": 247997,
        "Bridgewatch": 243402,
        "Caerleon": 0,
        "Brecilien": 0
      }
    },
    {
      "itemId": "T8_METALBAR_LEVEL3@3",
      "tier": 8,
      "enchant": 3,
      "prices": {
        "Lymhurst": 708984,
        "Martlock": 683995,
        "Fort Sterling": 681880,
        "Thetford": 672998,
        "Bridgewatch": 706647,
        "Caerleon": 899993,
        "Brecilien": 0
      }
    },
    {
      "itemId": "T8_METALBAR_LEVEL4@4",
      "tier": 8,
      "enchant": 4,
      "prices": {
        "Lymhurst": 3329996,
        "Martlock": 3350000,
        "Fort Sterling": 3299999,
        "Thetford": 3331996,
        "Bridgewatch": 3269999,
        "Caerleon": 3500000,
        "Brecilien": 0
      }
    },
    {
      "itemId": "T4_LEATHER",
      "tier": 4,
      "enchant": 0,
      "prices": {
        "Lymhurst": 296,
        "Martlock": 290,
        "Fort Sterling": 300,
        "Thetford": 279,
        "Bridgewatch": 291,
        "Caerleon": 445,
        "Brecilien": 271
      }
    },
    {
      "itemId": "T4_LEATHER_LEVEL1@1",
      "tier": 4,
      "enchant": 1,
      "prices": {
        "Lymhurst": 453,
        "Martlock": 384,
        "Fort Sterling": 425,
        "Thetford": 456,
        "Bridgewatch": 463,
        "Caerleon": 646,
        "Brecilien": 0
      }
    },
    {
      "itemId": "T4_LEATHER_LEVEL2@2",
      "tier": 4,
      "enchant": 2,
      "prices": {
        "Lymhurst": 2225,
        "Martlock": 2315,
        "Fort Sterling": 2144,
        "Thetford": 1862,
        "Bridgewatch": 2404,
        "Caerleon": 2399,
        "Brecilien": 0
      }
    },
    {
      "itemId": "T4_LEATHER_LEVEL3@3",
      "tier": 4,
      "enchant": 3,
      "prices": {
        "Lymhurst": 8859,
        "Martlock": 8680,
        "Fort Sterling": 9988,
        "Thetford": 9646,
        "Bridgewatch": 10797,
        "Caerleon": 9467,
        "Brecilien": 0
      }
    },
    {
      "itemId": "T4_LEATHER_LEVEL4@4",
      "tier": 4,
      "enchant": 4,
      "prices": {
        "Lymhurst": 41521,
        "Martlock": 41592,
        "Fort Sterling": 46986,
        "Thetford": 41900,
        "Bridgewatch": 42000,
        "Caerleon": 51415,
        "Brecilien": 42970
      }
    },
    {
      "itemId": "T5_LEATHER",
      "tier": 5,
      "enchant": 0,
      "prices": {
        "Lymhurst": 1373,
        "Martlock": 1241,
        "Fort Sterling": 1275,
        "Thetford": 1232,
        "Bridgewatch": 1237,
        "Caerleon": 1839,
        "Brecilien": 1285
      }
    },
    {
      "itemId": "T5_LEATHER_LEVEL1@1",
      "tier": 5,
      "enchant": 1,
      "prices": {
        "Lymhurst": 2025,
        "Martlock": 1929,
        "Fort Sterling": 1875,
        "Thetford": 1924,
        "Bridgewatch": 2100,
        "Caerleon": 2780,
        "Brecilien": 0
      }
    },
    {
      "itemId": "T5_LEATHER_LEVEL2@2",
      "tier": 5,
      "enchant": 2,
      "prices": {
        "Lymhurst": 7010,
        "Martlock": 7687,
        "Fort Sterling": 7349,
        "Thetford": 7480,
        "Bridgewatch": 8887,
        "Caerleon": 8188,
        "Brecilien": 0
      }
    },
    {
      "itemId": "T5_LEATHER_LEVEL3@3",
      "tier": 5,
      "enchant": 3,
      "prices": {
        "Lymhurst": 31389,
        "Martlock": 30030,
        "Fort Sterling": 30988,
        "Thetford": 29232,
        "Bridgewatch": 32999,
        "Caerleon": 29900,
        "Brecilien": 0
      }
    },
    {
      "itemId": "T5_LEATHER_LEVEL4@4",
      "tier": 5,
      "enchant": 4,
      "prices": {
        "Lymhurst": 123996,
        "Martlock": 98000,
        "Fort Sterling": 104409,
        "Thetford": 102000,
        "Bridgewatch": 109958,
        "Caerleon": 149999,
        "Brecilien": 0
      }
    },
    {
      "itemId": "T6_LEATHER",
      "tier": 6,
      "enchant": 0,
      "prices": {
        "Lymhurst": 5099,
        "Martlock": 4625,
        "Fort Sterling": 4893,
        "Thetford": 4896,
        "Bridgewatch": 4993,
        "Caerleon": 5791,
        "Brecilien": 5366
      }
    },
    {
      "itemId": "T6_LEATHER_LEVEL1@1",
      "tier": 6,
      "enchant": 1,
      "prices": {
        "Lymhurst": 9474,
        "Martlock": 8752,
        "Fort Sterling": 9030,
        "Thetford": 8738,
        "Bridgewatch": 9262,
        "Caerleon": 9372,
        "Brecilien": 0
      }
    },
    {
      "itemId": "T6_LEATHER_LEVEL2@2",
      "tier": 6,
      "enchant": 2,
      "prices": {
        "Lymhurst": 29200,
        "Martlock": 28567,
        "Fort Sterling": 31054,
        "Thetford": 29181,
        "Bridgewatch": 29998,
        "Caerleon": 34401,
        "Brecilien": 0
      }
    },
    {
      "itemId": "T6_LEATHER_LEVEL3@3",
      "tier": 6,
      "enchant": 3,
      "prices": {
        "Lymhurst": 95383,
        "Martlock": 95606,
        "Fort Sterling": 97497,
        "Thetford": 90994,
        "Bridgewatch": 97991,
        "Caerleon": 99801,
        "Brecilien": 0
      }
    },
    {
      "itemId": "T6_LEATHER_LEVEL4@4",
      "tier": 6,
      "enchant": 4,
      "prices": {
        "Lymhurst": 323993,
        "Martlock": 339995,
        "Fort Sterling": 360000,
        "Thetford": 328840,
        "Bridgewatch": 350000,
        "Caerleon": 369997,
        "Brecilien": 0
      }
    },
    {
      "itemId": "T7_LEATHER",
      "tier": 7,
      "enchant": 0,
      "prices": {
        "Lymhurst": 18207,
        "Martlock": 16970,
        "Fort Sterling": 16468,
        "Thetford": 16346,
        "Bridgewatch": 16485,
        "Caerleon": 20998,
        "Brecilien": 0
      }
    },
    {
      "itemId": "T7_LEATHER_LEVEL1@1",
      "tier": 7,
      "enchant": 1,
      "prices": {
        "Lymhurst": 32128,
        "Martlock": 32589,
        "Fort Sterling": 34821,
        "Thetford": 33486,
        "Bridgewatch": 33995,
        "Caerleon": 47393,
        "Brecilien": 49996
      }
    },
    {
      "itemId": "T7_LEATHER_LEVEL2@2",
      "tier": 7,
      "enchant": 2,
      "prices": {
        "Lymhurst": 86992,
        "Martlock": 94966,
        "Fort Sterling": 93955,
        "Thetford": 91985,
        "Bridgewatch": 99636,
        "Caerleon": 94947,
        "Brecilien": 0
      }
    },
    {
      "itemId": "T7_LEATHER_LEVEL3@3",
      "tier": 7,
      "enchant": 3,
      "prices": {
        "Lymhurst": 279987,
        "Martlock": 275969,
        "Fort Sterling": 279416,
        "Thetford": 287807,
        "Bridgewatch": 319988,
        "Caerleon": 399885,
        "Brecilien": 0
      }
    },
    {
      "itemId": "T7_LEATHER_LEVEL4@4",
      "tier": 7,
      "enchant": 4,
      "prices": {
        "Lymhurst": 1140000,
        "Martlock": 929991,
        "Fort Sterling": 1051423,
        "Thetford": 1399000,
        "Bridgewatch": 0,
        "Caerleon": 948999,
        "Brecilien": 0
      }
    },
    {
      "itemId": "T8_LEATHER",
      "tier": 8,
      "enchant": 0,
      "prices": {
        "Lymhurst": 43940,
        "Martlock": 40479,
        "Fort Sterling": 46909,
        "Thetford": 45979,
        "Bridgewatch": 44026,
        "Caerleon": 48769,
        "Brecilien": 0
      }
    },
    {
      "itemId": "T8_LEATHER_LEVEL1@1",
      "tier": 8,
      "enchant": 1,
      "prices": {
        "Lymhurst": 104429,
        "Martlock": 96897,
        "Fort Sterling": 99394,
        "Thetford": 105998,
        "Bridgewatch": 108978,
        "Caerleon": 104995,
        "Brecilien": 0
      }
    },
    {
      "itemId": "T8_LEATHER_LEVEL2@2",
      "tier": 8,
      "enchant": 2,
      "prices": {
        "Lymhurst": 319984,
        "Martlock": 284440,
        "Fort Sterling": 297997,
        "Thetford": 279999,
        "Bridgewatch": 300000,
        "Caerleon": 344999,
        "Brecilien": 0
      }
    },
    {
      "itemId": "T8_LEATHER_LEVEL3@3",
      "tier": 8,
      "enchant": 3,
      "prices": {
        "Lymhurst": 759996,
        "Martlock": 734996,
        "Fort Sterling": 748988,
        "Thetford": 764973,
        "Bridgewatch": 748997,
        "Caerleon": 849999,
        "Brecilien": 0
      }
    },
    {
      "itemId": "T8_LEATHER_LEVEL4@4",
      "tier": 8,
      "enchant": 4,
      "prices": {
        "Lymhurst": 3449982,
        "Martlock": 3199993,
        "Fort Sterling": 3385000,
        "Thetford": 3449997,
        "Bridgewatch": 3499993,
        "Caerleon": 0,
        "Brecilien": 0
      }
    },
    {
      "itemId": "T4_PLANKS",
      "tier": 4,
      "enchant": 0,
      "prices": {
        "Lymhurst": 293,
        "Martlock": 0,
        "Fort Sterling": 248,
        "Thetford": 300,
        "Bridgewatch": 302,
        "Caerleon": 454,
        "Brecilien": 0
      }
    },
    {
      "itemId": "T4_PLANKS_LEVEL1@1",
      "tier": 4,
      "enchant": 1,
      "prices": {
        "Lymhurst": 358,
        "Martlock": 0,
        "Fort Sterling": 303,
        "Thetford": 385,
        "Bridgewatch": 384,
        "Caerleon": 662,
        "Brecilien": 0
      }
    },
    {
      "itemId": "T4_PLANKS_LEVEL2@2",
      "tier": 4,
      "enchant": 2,
      "prices": {
        "Lymhurst": 1394,
        "Martlock": 1348,
        "Fort Sterling": 1454,
        "Thetford": 1407,
        "Bridgewatch": 1399,
        "Caerleon": 1695,
        "Brecilien": 0
      }
    },
    {
      "itemId": "T4_PLANKS_LEVEL3@3",
      "tier": 4,
      "enchant": 3,
      "prices": {
        "Lymhurst": 6999,
        "Martlock": 0,
        "Fort Sterling": 7150,
        "Thetford": 7545,
        "Bridgewatch": 7950,
        "Caerleon": 7490,
        "Brecilien": 0
      }
    },
    {
      "itemId": "T4_PLANKS_LEVEL4@4",
      "tier": 4,
      "enchant": 4,
      "prices": {
        "Lymhurst": 41954,
        "Martlock": 46475,
        "Fort Sterling": 42475,
        "Thetford": 43300,
        "Bridgewatch": 42698,
        "Caerleon": 39998,
        "Brecilien": 44999
      }
    },
    {
      "itemId": "T5_PLANKS",
      "tier": 5,
      "enchant": 0,
      "prices": {
        "Lymhurst": 820,
        "Martlock": 0,
        "Fort Sterling": 767,
        "Thetford": 803,
        "Bridgewatch": 889,
        "Caerleon": 1021,
        "Brecilien": 0
      }
    },
    {
      "itemId": "T5_PLANKS_LEVEL1@1",
      "tier": 5,
      "enchant": 1,
      "prices": {
        "Lymhurst": 1222,
        "Martlock": 1290,
        "Fort Sterling": 1167,
        "Thetford": 1242,
        "Bridgewatch": 1309,
        "Caerleon": 1549,
        "Brecilien": 0
      }
    },
    {
      "itemId": "T5_PLANKS_LEVEL2@2",
      "tier": 5,
      "enchant": 2,
      "prices": {
        "Lymhurst": 5026,
        "Martlock": 4974,
        "Fort Sterling": 4903,
        "Thetford": 5465,
        "Bridgewatch": 6197,
        "Caerleon": 6399,
        "Brecilien": 0
      }
    },
    {
      "itemId": "T5_PLANKS_LEVEL3@3",
      "tier": 5,
      "enchant": 3,
      "prices": {
        "Lymhurst": 26848,
        "Martlock": 0,
        "Fort Sterling": 27997,
        "Thetford": 27999,
        "Bridgewatch": 30000,
        "Caerleon": 25966,
        "Brecilien": 0
      }
    },
    {
      "itemId": "T5_PLANKS_LEVEL4@4",
      "tier": 5,
      "enchant": 4,
      "prices": {
        "Lymhurst": 125000,
        "Martlock": 127489,
        "Fort Sterling": 124169,
        "Thetford": 116000,
        "Bridgewatch": 144999,
        "Caerleon": 130420,
        "Brecilien": 0
      }
    },
    {
      "itemId": "T6_PLANKS",
      "tier": 6,
      "enchant": 0,
      "prices": {
        "Lymhurst": 2921,
        "Martlock": 0,
        "Fort Sterling": 2940,
        "Thetford": 3035,
        "Bridgewatch": 3068,
        "Caerleon": 3202,
        "Brecilien": 0
      }
    },
    {
      "itemId": "T6_PLANKS_LEVEL1@1",
      "tier": 6,
      "enchant": 1,
      "prices": {
        "Lymhurst": 5700,
        "Martlock": 5774,
        "Fort Sterling": 5461,
        "Thetford": 5546,
        "Bridgewatch": 5728,
        "Caerleon": 5473,
        "Brecilien": 0
      }
    },
    {
      "itemId": "T6_PLANKS_LEVEL2@2",
      "tier": 6,
      "enchant": 2,
      "prices": {
        "Lymhurst": 21178,
        "Martlock": 22377,
        "Fort Sterling": 20976,
        "Thetford": 22984,
        "Bridgewatch": 21241,
        "Caerleon": 29894,
        "Brecilien": 0
      }
    },
    {
      "itemId": "T6_PLANKS_LEVEL3@3",
      "tier": 6,
      "enchant": 3,
      "prices": {
        "Lymhurst": 82875,
        "Martlock": 94995,
        "Fort Sterling": 84043,
        "Thetford": 91993,
        "Bridgewatch": 87887,
        "Caerleon": 86499,
        "Brecilien": 0
      }
    },
    {
      "itemId": "T6_PLANKS_LEVEL4@4",
      "tier": 6,
      "enchant": 4,
      "prices": {
        "Lymhurst": 364577,
        "Martlock": 369998,
        "Fort Sterling": 340000,
        "Thetford": 379987,
        "Bridgewatch": 369995,
        "Caerleon": 599996,
        "Brecilien": 0
      }
    },
    {
      "itemId": "T7_PLANKS",
      "tier": 7,
      "enchant": 0,
      "prices": {
        "Lymhurst": 10697,
        "Martlock": 0,
        "Fort Sterling": 10893,
        "Thetford": 12000,
        "Bridgewatch": 11170,
        "Caerleon": 11483,
        "Brecilien": 0
      }
    },
    {
      "itemId": "T7_PLANKS_LEVEL1@1",
      "tier": 7,
      "enchant": 1,
      "prices": {
        "Lymhurst": 18909,
        "Martlock": 18985,
        "Fort Sterling": 17893,
        "Thetford": 17972,
        "Bridgewatch": 18955,
        "Caerleon": 29987,
        "Brecilien": 0
      }
    },
    {
      "itemId": "T7_PLANKS_LEVEL2@2",
      "tier": 7,
      "enchant": 2,
      "prices": {
        "Lymhurst": 65097,
        "Martlock": 74495,
        "Fort Sterling": 66400,
        "Thetford": 65000,
        "Bridgewatch": 64979,
        "Caerleon": 69997,
        "Brecilien": 0
      }
    },
    {
      "itemId": "T7_PLANKS_LEVEL3@3",
      "tier": 7,
      "enchant": 3,
      "prices": {
        "Lymhurst": 259969,
        "Martlock": 319999,
        "Fort Sterling": 249984,
        "Thetford": 274996,
        "Bridgewatch": 0,
        "Caerleon": 265992,
        "Brecilien": 0
      }
    },
    {
      "itemId": "T7_PLANKS_LEVEL4@4",
      "tier": 7,
      "enchant": 4,
      "prices": {
        "Lymhurst": 1199995,
        "Martlock": 1246999,
        "Fort Sterling": 1030000,
        "Thetford": 1388877,
        "Bridgewatch": 1199995,
        "Caerleon": 999999,
        "Brecilien": 0
      }
    },
    {
      "itemId": "T8_PLANKS",
      "tier": 8,
      "enchant": 0,
      "prices": {
        "Lymhurst": 37295,
        "Martlock": 0,
        "Fort Sterling": 37275,
        "Thetford": 37877,
        "Bridgewatch": 38794,
        "Caerleon": 39999,
        "Brecilien": 0
      }
    },
    {
      "itemId": "T8_PLANKS_LEVEL1@1",
      "tier": 8,
      "enchant": 1,
      "prices": {
        "Lymhurst": 57284,
        "Martlock": 56940,
        "Fort Sterling": 55700,
        "Thetford": 51998,
        "Bridgewatch": 54418,
        "Caerleon": 59939,
        "Brecilien": 0
      }
    },
    {
      "itemId": "T8_PLANKS_LEVEL2@2",
      "tier": 8,
      "enchant": 2,
      "prices": {
        "Lymhurst": 208995,
        "Martlock": 239386,
        "Fort Sterling": 234535,
        "Thetford": 209999,
        "Bridgewatch": 214999,
        "Caerleon": 249994,
        "Brecilien": 0
      }
    },
    {
      "itemId": "T8_PLANKS_LEVEL3@3",
      "tier": 8,
      "enchant": 3,
      "prices": {
        "Lymhurst": 674947,
        "Martlock": 682897,
        "Fort Sterling": 684998,
        "Thetford": 699973,
        "Bridgewatch": 672872,
        "Caerleon": 749997,
        "Brecilien": 0
      }
    },
    {
      "itemId": "T8_PLANKS_LEVEL4@4",
      "tier": 8,
      "enchant": 4,
      "prices": {
        "Lymhurst": 3499896,
        "Martlock": 3400000,
        "Fort Sterling": 3349995,
        "Thetford": 0,
        "Bridgewatch": 3599000,
        "Caerleon": 0,
        "Brecilien": 0
      }
    },
    {
      "itemId": "T4_CLOTH",
      "tier": 4,
      "enchant": 0,
      "prices": {
        "Lymhurst": 233,
        "Martlock": 277,
        "Fort Sterling": 258,
        "Thetford": 288,
        "Bridgewatch": 265,
        "Caerleon": 445,
        "Brecilien": 0
      }
    },
    {
      "itemId": "T4_CLOTH_LEVEL1@1",
      "tier": 4,
      "enchant": 1,
      "prices": {
        "Lymhurst": 328,
        "Martlock": 390,
        "Fort Sterling": 378,
        "Thetford": 329,
        "Bridgewatch": 339,
        "Caerleon": 493,
        "Brecilien": 0
      }
    },
    {
      "itemId": "T4_CLOTH_LEVEL2@2",
      "tier": 4,
      "enchant": 2,
      "prices": {
        "Lymhurst": 1805,
        "Martlock": 1998,
        "Fort Sterling": 1950,
        "Thetford": 1965,
        "Bridgewatch": 1910,
        "Caerleon": 2445,
        "Brecilien": 0
      }
    },
    {
      "itemId": "T4_CLOTH_LEVEL3@3",
      "tier": 4,
      "enchant": 3,
      "prices": {
        "Lymhurst": 7420,
        "Martlock": 6997,
        "Fort Sterling": 6992,
        "Thetford": 7324,
        "Bridgewatch": 7648,
        "Caerleon": 8475,
        "Brecilien": 0
      }
    },
    {
      "itemId": "T4_CLOTH_LEVEL4@4",
      "tier": 4,
      "enchant": 4,
      "prices": {
        "Lymhurst": 40081,
        "Martlock": 44998,
        "Fort Sterling": 40926,
        "Thetford": 43987,
        "Bridgewatch": 45436,
        "Caerleon": 49998,
        "Brecilien": 0
      }
    },
    {
      "itemId": "T5_CLOTH",
      "tier": 5,
      "enchant": 0,
      "prices": {
        "Lymhurst": 849,
        "Martlock": 935,
        "Fort Sterling": 836,
        "Thetford": 908,
        "Bridgewatch": 879,
        "Caerleon": 1026,
        "Brecilien": 0
      }
    },
    {
      "itemId": "T5_CLOTH_LEVEL1@1",
      "tier": 5,
      "enchant": 1,
      "prices": {
        "Lymhurst": 1913,
        "Martlock": 1832,
        "Fort Sterling": 1829,
        "Thetford": 1861,
        "Bridgewatch": 1984,
        "Caerleon": 0,
        "Brecilien": 0
      }
    },
    {
      "itemId": "T5_CLOTH_LEVEL2@2",
      "tier": 5,
      "enchant": 2,
      "prices": {
        "Lymhurst": 4597,
        "Martlock": 4371,
        "Fort Sterling": 4146,
        "Thetford": 4303,
        "Bridgewatch": 4649,
        "Caerleon": 4965,
        "Brecilien": 0
      }
    },
    {
      "itemId": "T5_CLOTH_LEVEL3@3",
      "tier": 5,
      "enchant": 3,
      "prices": {
        "Lymhurst": 20847,
        "Martlock": 21400,
        "Fort Sterling": 20078,
        "Thetford": 20134,
        "Bridgewatch": 21384,
        "Caerleon": 19660,
        "Brecilien": 0
      }
    },
    {
      "itemId": "T5_CLOTH_LEVEL4@4",
      "tier": 5,
      "enchant": 4,
      "prices": {
        "Lymhurst": 90065,
        "Martlock": 104178,
        "Fort Sterling": 96660,
        "Thetford": 103315,
        "Bridgewatch": 99864,
        "Caerleon": 137998,
        "Brecilien": 0
      }
    },
    {
      "itemId": "T6_CLOTH",
      "tier": 6,
      "enchant": 0,
      "prices": {
        "Lymhurst": 3106,
        "Martlock": 3319,
        "Fort Sterling": 3019,
        "Thetford": 3097,
        "Bridgewatch": 3069,
        "Caerleon": 3889,
        "Brecilien": 0
      }
    },
    {
      "itemId": "T6_CLOTH_LEVEL1@1",
      "tier": 6,
      "enchant": 1,
      "prices": {
        "Lymhurst": 5446,
        "Martlock": 6284,
        "Fort Sterling": 5854,
        "Thetford": 5387,
        "Bridgewatch": 5794,
        "Caerleon": 7446,
        "Brecilien": 0
      }
    },
    {
      "itemId": "T6_CLOTH_LEVEL2@2",
      "tier": 6,
      "enchant": 2,
      "prices": {
        "Lymhurst": 17555,
        "Martlock": 20485,
        "Fort Sterling": 17685,
        "Thetford": 19775,
        "Bridgewatch": 19838,
        "Caerleon": 17975,
        "Brecilien": 0
      }
    },
    {
      "itemId": "T6_CLOTH_LEVEL3@3",
      "tier": 6,
      "enchant": 3,
      "prices": {
        "Lymhurst": 47006,
        "Martlock": 50981,
        "Fort Sterling": 45984,
        "Thetford": 46998,
        "Bridgewatch": 51869,
        "Caerleon": 51982,
        "Brecilien": 0
      }
    },
    {
      "itemId": "T6_CLOTH_LEVEL4@4",
      "tier": 6,
      "enchant": 4,
      "prices": {
        "Lymhurst": 270983,
        "Martlock": 267995,
        "Fort Sterling": 302090,
        "Thetford": 274959,
        "Bridgewatch": 276999,
        "Caerleon": 349992,
        "Brecilien": 0
      }
    },
    {
      "itemId": "T7_CLOTH",
      "tier": 7,
      "enchant": 0,
      "prices": {
        "Lymhurst": 8027,
        "Martlock": 7489,
        "Fort Sterling": 8139,
        "Thetford": 8199,
        "Bridgewatch": 8181,
        "Caerleon": 9994,
        "Brecilien": 0
      }
    },
    {
      "itemId": "T7_CLOTH_LEVEL1@1",
      "tier": 7,
      "enchant": 1,
      "prices": {
        "Lymhurst": 19153,
        "Martlock": 19468,
        "Fort Sterling": 18892,
        "Thetford": 19972,
        "Bridgewatch": 18498,
        "Caerleon": 25378,
        "Brecilien": 0
      }
    },
    {
      "itemId": "T7_CLOTH_LEVEL2@2",
      "tier": 7,
      "enchant": 2,
      "prices": {
        "Lymhurst": 51484,
        "Martlock": 64949,
        "Fort Sterling": 51988,
        "Thetford": 53582,
        "Bridgewatch": 52223,
        "Caerleon": 74942,
        "Brecilien": 0
      }
    },
    {
      "itemId": "T7_CLOTH_LEVEL3@3",
      "tier": 7,
      "enchant": 3,
      "prices": {
        "Lymhurst": 200422,
        "Martlock": 205974,
        "Fort Sterling": 200815,
        "Thetford": 200000,
        "Bridgewatch": 203869,
        "Caerleon": 250000,
        "Brecilien": 0
      }
    },
    {
      "itemId": "T7_CLOTH_LEVEL4@4",
      "tier": 7,
      "enchant": 4,
      "prices": {
        "Lymhurst": 849998,
        "Martlock": 884097,
        "Fort Sterling": 864063,
        "Thetford": 829000,
        "Bridgewatch": 849991,
        "Caerleon": 0,
        "Brecilien": 0
      }
    },
    {
      "itemId": "T8_CLOTH",
      "tier": 8,
      "enchant": 0,
      "prices": {
        "Lymhurst": 28903,
        "Martlock": 28993,
        "Fort Sterling": 28993,
        "Thetford": 31991,
        "Bridgewatch": 31262,
        "Caerleon": 30492,
        "Brecilien": 0
      }
    },
    {
      "itemId": "T8_CLOTH_LEVEL1@1",
      "tier": 8,
      "enchant": 1,
      "prices": {
        "Lymhurst": 67467,
        "Martlock": 69078,
        "Fort Sterling": 68736,
        "Thetford": 55550,
        "Bridgewatch": 68977,
        "Caerleon": 79898,
        "Brecilien": 0
      }
    },
    {
      "itemId": "T8_CLOTH_LEVEL2@2",
      "tier": 8,
      "enchant": 2,
      "prices": {
        "Lymhurst": 213934,
        "Martlock": 229989,
        "Fort Sterling": 225990,
        "Thetford": 228990,
        "Bridgewatch": 217000,
        "Caerleon": 294877,
        "Brecilien": 0
      }
    },
    {
      "itemId": "T8_CLOTH_LEVEL3@3",
      "tier": 8,
      "enchant": 3,
      "prices": {
        "Lymhurst": 674878,
        "Martlock": 692993,
        "Fort Sterling": 692991,
        "Thetford": 693993,
        "Bridgewatch": 744999,
        "Caerleon": 799997,
        "Brecilien": 0
      }
    },
    {
      "itemId": "T8_CLOTH_LEVEL4@4",
      "tier": 8,
      "enchant": 4,
      "prices": {
        "Lymhurst": 3307963,
        "Martlock": 3399997,
        "Fort Sterling": 3388886,
        "Thetford": 3430000,
        "Bridgewatch": 3349995,
        "Caerleon": 3349998,
        "Brecilien": 0
      }
    },
    {
      "itemId": "T4_STONEBLOCK",
      "tier": 4,
      "enchant": 0,
      "prices": {
        "Lymhurst": 273,
        "Martlock": 258,
        "Fort Sterling": 301,
        "Thetford": 300,
        "Bridgewatch": 184,
        "Caerleon": 0,
        "Brecilien": 218
      }
    },
    {
      "itemId": "T5_STONEBLOCK",
      "tier": 5,
      "enchant": 0,
      "prices": {
        "Lymhurst": 442,
        "Martlock": 375,
        "Fort Sterling": 427,
        "Thetford": 360,
        "Bridgewatch": 343,
        "Caerleon": 329,
        "Brecilien": 0
      }
    },
    {
      "itemId": "T6_STONEBLOCK",
      "tier": 6,
      "enchant": 0,
      "prices": {
        "Lymhurst": 1641,
        "Martlock": 1640,
        "Fort Sterling": 1799,
        "Thetford": 1899,
        "Bridgewatch": 1589,
        "Caerleon": 2371,
        "Brecilien": 1699
      }
    },
    {
      "itemId": "T7_STONEBLOCK",
      "tier": 7,
      "enchant": 0,
      "prices": {
        "Lymhurst": 8500,
        "Martlock": 8697,
        "Fort Sterling": 9234,
        "Thetford": 8499,
        "Bridgewatch": 8483,
        "Caerleon": 8442,
        "Brecilien": 0
      }
    },
    {
      "itemId": "T8_STONEBLOCK",
      "tier": 8,
      "enchant": 0,
      "prices": {
        "Lymhurst": 37965,
        "Martlock": 37926,
        "Fort Sterling": 36997,
        "Thetford": 38111,
        "Bridgewatch": 36164,
        "Caerleon": 34995,
        "Brecilien": 0
      }
    }
  ]
}
