{
  "generatedAt": "2026-06-04T08:21:30.202Z",
  "region": "us",
  "cities": [
    "Lymhurst",
    "Martlock",
    "Fort Sterling",
    "Thetford",
    "Bridgewatch",
    "Caerleon",
    "Brecilien"
  ],
  "count": 172,
  "items": [
    {
      "itemId": "T2_POTION_ENERGY",
      "tier": 2,
      "prices": {
        "Lymhurst": 210,
        "Fort Sterling": 297,
        "Thetford": 168,
        "Bridgewatch": 387,
        "Brecilien": 288
      },
      "sold": 10293
    },
    {
      "itemId": "T2_POTION_HEAL",
      "tier": 2,
      "prices": {
        "Lymhurst": 196,
        "Martlock": 146,
        "Fort Sterling": 289,
        "Thetford": 139,
        "Bridgewatch": 228,
        "Caerleon": 253,
        "Brecilien": 264
      },
      "sold": 21115
    },
    {
      "itemId": "T3_POTION_ACID",
      "tier": 3,
      "prices": {
        "Lymhurst": 5980,
        "Fort Sterling": 7483,
        "Caerleon": 8348,
        "Brecilien": 5984
      },
      "sold": 6007
    },
    {
      "itemId": "T3_POTION_MOB_RESET",
      "tier": 3,
      "prices": {
        "Lymhurst": 7998,
        "Martlock": 8129,
        "Fort Sterling": 8144,
        "Bridgewatch": 8226,
        "Caerleon": 8883,
        "Brecilien": 7128
      },
      "sold": 9587
    },
    {
      "itemId": "T3_POTION_CLEANSE2",
      "tier": 3,
      "prices": {
        "Lymhurst": 1844,
        "Fort Sterling": 2160,
        "Brecilien": 2349
      },
      "sold": 663
    },
    {
      "itemId": "T3_POTION_REVIVE",
      "tier": 3,
      "prices": {
        "Lymhurst": 635,
        "Martlock": 493,
        "Fort Sterling": 609,
        "Thetford": 612,
        "Bridgewatch": 451,
        "Caerleon": 318,
        "Brecilien": 441
      },
      "sold": 49268
    },
    {
      "itemId": "T3_POTION_STONESKIN",
      "tier": 3,
      "prices": {
        "Lymhurst": 476,
        "Martlock": 233,
        "Fort Sterling": 445,
        "Bridgewatch": 520,
        "Caerleon": 293,
        "Brecilien": 721
      },
      "sold": 10473
    },
    {
      "itemId": "T3_POTION_SLOWFIELD",
      "tier": 3,
      "prices": {
        "Lymhurst": 317,
        "Martlock": 331,
        "Fort Sterling": 339,
        "Thetford": 472,
        "Bridgewatch": 383,
        "Caerleon": 411,
        "Brecilien": 271
      },
      "sold": 10394
    },
    {
      "itemId": "T4_POTION_ENERGY",
      "tier": 4,
      "prices": {
        "Lymhurst": 2795,
        "Martlock": 3473,
        "Fort Sterling": 2199,
        "Thetford": 3233,
        "Bridgewatch": 2760,
        "Caerleon": 7989,
        "Brecilien": 2545
      },
      "sold": 19257
    },
    {
      "itemId": "T4_POTION_HEAL",
      "tier": 4,
      "prices": {
        "Lymhurst": 2318,
        "Fort Sterling": 2460,
        "Thetford": 1971,
        "Caerleon": 2600,
        "Brecilien": 2387
      },
      "sold": 17250
    },
    {
      "itemId": "T4_POTION_BERSERK",
      "tier": 4,
      "prices": {
        "Lymhurst": 2986,
        "Martlock": 2942,
        "Fort Sterling": 2274,
        "Brecilien": 3998
      },
      "sold": 1250
    },
    {
      "itemId": "T4_POTION_GATHER",
      "tier": 4,
      "prices": {
        "Lymhurst": 2210,
        "Fort Sterling": 2433,
        "Thetford": 2165,
        "Caerleon": 2496,
        "Brecilien": 2296
      },
      "sold": 4942
    },
    {
      "itemId": "T4_POTION_LAVA",
      "tier": 4,
      "prices": {
        "Lymhurst": 4034,
        "Fort Sterling": 4389,
        "Thetford": 3993,
        "Caerleon": 4294,
        "Brecilien": 2780
      },
      "sold": 6652
    },
    {
      "itemId": "T4_POTION_COOLDOWN",
      "tier": 4,
      "prices": {
        "Lymhurst": 667,
        "Martlock": 660,
        "Fort Sterling": 630,
        "Thetford": 651,
        "Bridgewatch": 668,
        "Caerleon": 554,
        "Brecilien": 606
      },
      "sold": 133468
    },
    {
      "itemId": "T4_POTION_TORNADO",
      "tier": 4,
      "prices": {
        "Lymhurst": 1969,
        "Martlock": 3082,
        "Fort Sterling": 2011,
        "Thetford": 2293,
        "Caerleon": 4241,
        "Brecilien": 2202
      },
      "sold": 6661
    },
    {
      "itemId": "T5_POTION_ACID",
      "tier": 5,
      "prices": {
        "Lymhurst": 10960,
        "Martlock": 17498,
        "Fort Sterling": 14121,
        "Thetford": 12149,
        "Caerleon": 14939,
        "Brecilien": 13236
      },
      "sold": 3014
    },
    {
      "itemId": "T5_POTION_MOB_RESET",
      "tier": 5,
      "prices": {
        "Lymhurst": 18396,
        "Fort Sterling": 17837,
        "Caerleon": 20000,
        "Brecilien": 16491
      },
      "sold": 6310
    },
    {
      "itemId": "T5_POTION_CLEANSE2",
      "tier": 5,
      "prices": {
        "Lymhurst": 9060,
        "Fort Sterling": 6997,
        "Caerleon": 11436,
        "Brecilien": 8889
      },
      "sold": 1691
    },
    {
      "itemId": "T5_POTION_REVIVE",
      "tier": 5,
      "prices": {
        "Lymhurst": 3573,
        "Martlock": 3829,
        "Fort Sterling": 3901,
        "Thetford": 3765,
        "Bridgewatch": 3463,
        "Caerleon": 3519,
        "Brecilien": 3363
      },
      "sold": 51798
    },
    {
      "itemId": "T5_POTION_STONESKIN",
      "tier": 5,
      "prices": {
        "Lymhurst": 3833,
        "Martlock": 3890,
        "Fort Sterling": 3786,
        "Thetford": 3635,
        "Bridgewatch": 3597,
        "Caerleon": 3690,
        "Brecilien": 4035
      },
      "sold": 11355
    },
    {
      "itemId": "T5_POTION_SLOWFIELD",
      "tier": 5,
      "prices": {
        "Lymhurst": 2253,
        "Martlock": 2137,
        "Fort Sterling": 2190,
        "Thetford": 1770,
        "Caerleon": 3963,
        "Brecilien": 1982
      },
      "sold": 5615
    },
    {
      "itemId": "T6_POTION_BERSERK",
      "tier": 6,
      "prices": {
        "Lymhurst": 5996,
        "Fort Sterling": 5327,
        "Caerleon": 4996,
        "Brecilien": 5740
      },
      "sold": 978
    },
    {
      "itemId": "T6_POTION_GATHER",
      "tier": 6,
      "prices": {
        "Lymhurst": 9300,
        "Martlock": 7988,
        "Fort Sterling": 8344,
        "Thetford": 7974,
        "Caerleon": 9991,
        "Brecilien": 8093
      },
      "sold": 11925
    },
    {
      "itemId": "T6_POTION_LAVA",
      "tier": 6,
      "prices": {
        "Lymhurst": 8638,
        "Martlock": 8412,
        "Fort Sterling": 8927,
        "Thetford": 8242,
        "Caerleon": 9338,
        "Brecilien": 7943
      },
      "sold": 5884
    },
    {
      "itemId": "T6_POTION_ENERGY",
      "tier": 6,
      "prices": {
        "Lymhurst": 8970,
        "Fort Sterling": 7945,
        "Caerleon": 5940998,
        "Brecilien": 7790
      },
      "sold": 7627
    },
    {
      "itemId": "T6_POTION_HEAL",
      "tier": 6,
      "prices": {
        "Lymhurst": 8449,
        "Martlock": 7188,
        "Fort Sterling": 8393,
        "Thetford": 7287,
        "Bridgewatch": 8119,
        "Caerleon": 8078,
        "Brecilien": 7058
      },
      "sold": 31762
    },
    {
      "itemId": "T6_POTION_COOLDOWN",
      "tier": 6,
      "prices": {
        "Lymhurst": 4670,
        "Martlock": 4349,
        "Fort Sterling": 4912,
        "Thetford": 4568,
        "Bridgewatch": 4902,
        "Caerleon": 4850,
        "Brecilien": 3999
      },
      "sold": 27214
    },
    {
      "itemId": "T6_ALCOHOL",
      "tier": 6,
      "prices": {
        "Lymhurst": 688,
        "Martlock": 335,
        "Fort Sterling": 314,
        "Thetford": 366,
        "Caerleon": 255,
        "Brecilien": 417
      },
      "sold": 40329
    },
    {
      "itemId": "T6_POTION_TORNADO",
      "tier": 6,
      "prices": {
        "Lymhurst": 8859,
        "Martlock": 7069,
        "Fort Sterling": 9084,
        "Thetford": 7248,
        "Bridgewatch": 8633,
        "Caerleon": 11253,
        "Brecilien": 8444
      },
      "sold": 4980
    },
    {
      "itemId": "T7_ALCOHOL",
      "tier": 7,
      "prices": {
        "Lymhurst": 469,
        "Martlock": 441,
        "Fort Sterling": 370,
        "Thetford": 500,
        "Bridgewatch": 383,
        "Caerleon": 314,
        "Brecilien": 431
      },
      "sold": 59515
    },
    {
      "itemId": "T7_POTION_ACID",
      "tier": 7,
      "prices": {
        "Lymhurst": 31777,
        "Fort Sterling": 32379,
        "Caerleon": 34456,
        "Brecilien": 29889
      },
      "sold": 963
    },
    {
      "itemId": "T7_POTION_MOB_RESET",
      "tier": 7,
      "prices": {
        "Lymhurst": 53502,
        "Fort Sterling": 39930,
        "Brecilien": 44874
      },
      "sold": 557
    },
    {
      "itemId": "T7_POTION_CLEANSE2",
      "tier": 7,
      "prices": {
        "Lymhurst": 29752,
        "Martlock": 37890,
        "Fort Sterling": 39874,
        "Caerleon": 39873,
        "Brecilien": 32972
      },
      "sold": 1009
    },
    {
      "itemId": "T7_POTION_REVIVE",
      "tier": 7,
      "prices": {
        "Lymhurst": 10869,
        "Martlock": 10305,
        "Fort Sterling": 10908,
        "Thetford": 10782,
        "Bridgewatch": 10895,
        "Caerleon": 9550,
        "Brecilien": 10683
      },
      "sold": 112220
    },
    {
      "itemId": "T7_POTION_STONESKIN",
      "tier": 7,
      "prices": {
        "Lymhurst": 14253,
        "Martlock": 13377,
        "Fort Sterling": 14471,
        "Thetford": 11600,
        "Bridgewatch": 13391,
        "Caerleon": 16978,
        "Brecilien": 12988
      },
      "sold": 19053
    },
    {
      "itemId": "T7_POTION_SLOWFIELD",
      "tier": 7,
      "prices": {
        "Lymhurst": 12785,
        "Martlock": 36914,
        "Fort Sterling": 12790,
        "Caerleon": 14000,
        "Brecilien": 11493
      },
      "sold": 2473
    },
    {
      "itemId": "T8_POTION_CLEANSE",
      "tier": 8,
      "prices": {
        "Lymhurst": 13089,
        "Martlock": 13069,
        "Fort Sterling": 12878,
        "Thetford": 13334,
        "Bridgewatch": 13239,
        "Caerleon": 12983,
        "Brecilien": 12654
      },
      "sold": 49037
    },
    {
      "itemId": "T8_POTION_BERSERK",
      "tier": 8,
      "prices": {
        "Lymhurst": 14787,
        "Fort Sterling": 10923,
        "Caerleon": 15698,
        "Brecilien": 12388
      },
      "sold": 777
    },
    {
      "itemId": "T8_POTION_GATHER",
      "tier": 8,
      "prices": {
        "Lymhurst": 22200,
        "Fort Sterling": 22359,
        "Thetford": 22694,
        "Bridgewatch": 22499,
        "Caerleon": 34914,
        "Brecilien": 20990
      },
      "sold": 6210
    },
    {
      "itemId": "T8_POTION_LAVA",
      "tier": 8,
      "prices": {
        "Lymhurst": 29906,
        "Martlock": 26436,
        "Fort Sterling": 28347,
        "Thetford": 26915,
        "Caerleon": 42986,
        "Brecilien": 26883
      },
      "sold": 5369
    },
    {
      "itemId": "T8_POTION_COOLDOWN",
      "tier": 8,
      "prices": {
        "Lymhurst": 13842,
        "Fort Sterling": 12899,
        "Thetford": 13999,
        "Bridgewatch": 13000,
        "Caerleon": 20000000,
        "Brecilien": 12800
      },
      "sold": 39258
    },
    {
      "itemId": "T8_POTION_TORNADO",
      "tier": 8,
      "prices": {
        "Lymhurst": 13799,
        "Fort Sterling": 16787,
        "Thetford": 13700,
        "Caerleon": 22993,
        "Brecilien": 17375
      },
      "sold": 1603
    },
    {
      "itemId": "T8_ALCOHOL",
      "tier": 8,
      "prices": {
        "Lymhurst": 380,
        "Martlock": 421,
        "Fort Sterling": 357,
        "Thetford": 368,
        "Caerleon": 288,
        "Brecilien": 342
      },
      "sold": 54109
    },
    {
      "itemId": "T2_POTION_ENERGY@1",
      "tier": 2,
      "prices": {
        "Fort Sterling": 37998,
        "Thetford": 7988
      },
      "sold": 5
    },
    {
      "itemId": "T2_POTION_ENERGY@2",
      "tier": 2,
      "prices": {}
    },
    {
      "itemId": "T2_POTION_ENERGY@3",
      "tier": 2,
      "prices": {
        "Thetford": 15550
      },
      "sold": 1
    },
    {
      "itemId": "T2_POTION_HEAL@1",
      "tier": 2,
      "prices": {},
      "sold": 16
    },
    {
      "itemId": "T2_POTION_HEAL@2",
      "tier": 2,
      "prices": {},
      "sold": 4
    },
    {
      "itemId": "T2_POTION_HEAL@3",
      "tier": 2,
      "prices": {},
      "sold": 6
    },
    {
      "itemId": "T3_POTION_ACID@1",
      "tier": 3,
      "prices": {
        "Lymhurst": 7998,
        "Fort Sterling": 12990,
        "Thetford": 20000,
        "Caerleon": 14998,
        "Brecilien": 19995
      },
      "sold": 74
    },
    {
      "itemId": "T3_POTION_ACID@2",
      "tier": 3,
      "prices": {
        "Lymhurst": 11900,
        "Fort Sterling": 14999,
        "Brecilien": 19695
      },
      "sold": 36
    },
    {
      "itemId": "T3_POTION_ACID@3",
      "tier": 3,
      "prices": {
        "Brecilien": 24554
      }
    },
    {
      "itemId": "T3_POTION_MOB_RESET@1",
      "tier": 3,
      "prices": {
        "Lymhurst": 9927,
        "Martlock": 9921,
        "Fort Sterling": 9783,
        "Bridgewatch": 9299,
        "Caerleon": 11710,
        "Brecilien": 8566
      },
      "sold": 18085
    },
    {
      "itemId": "T3_POTION_MOB_RESET@2",
      "tier": 3,
      "prices": {
        "Lymhurst": 12199,
        "Martlock": 12480,
        "Fort Sterling": 12956,
        "Bridgewatch": 12361,
        "Caerleon": 14702,
        "Brecilien": 12126
      },
      "sold": 19923
    },
    {
      "itemId": "T3_POTION_MOB_RESET@3",
      "tier": 3,
      "prices": {
        "Lymhurst": 43500,
        "Fort Sterling": 58998,
        "Brecilien": 99999
      },
      "sold": 18
    },
    {
      "itemId": "T3_POTION_CLEANSE2@1",
      "tier": 3,
      "prices": {
        "Lymhurst": 40546,
        "Martlock": 4498,
        "Fort Sterling": 11989,
        "Caerleon": 9998
      },
      "sold": 8
    },
    {
      "itemId": "T3_POTION_CLEANSE2@2",
      "tier": 3,
      "prices": {
        "Fort Sterling": 14995,
        "Caerleon": 16666,
        "Brecilien": 11993
      },
      "sold": 4
    },
    {
      "itemId": "T3_POTION_CLEANSE2@3",
      "tier": 3,
      "prices": {
        "Fort Sterling": 9999,
        "Caerleon": 200000
      }
    },
    {
      "itemId": "T3_POTION_REVIVE@1",
      "tier": 3,
      "prices": {
        "Lymhurst": 8155,
        "Martlock": 7000,
        "Fort Sterling": 7990,
        "Caerleon": 7974,
        "Brecilien": 4725
      },
      "sold": 83
    },
    {
      "itemId": "T3_POTION_REVIVE@2",
      "tier": 3,
      "prices": {
        "Lymhurst": 11973,
        "Fort Sterling": 19999,
        "Caerleon": 7499,
        "Brecilien": 14985
      },
      "sold": 14
    },
    {
      "itemId": "T3_POTION_REVIVE@3",
      "tier": 3,
      "prices": {
        "Brecilien": 59970
      },
      "sold": 7
    },
    {
      "itemId": "T3_POTION_STONESKIN@1",
      "tier": 3,
      "prices": {
        "Lymhurst": 12496,
        "Fort Sterling": 7777,
        "Caerleon": 9000,
        "Brecilien": 5993
      },
      "sold": 9
    },
    {
      "itemId": "T3_POTION_STONESKIN@2",
      "tier": 3,
      "prices": {
        "Lymhurst": 10994,
        "Fort Sterling": 11800,
        "Brecilien": 9999
      },
      "sold": 2
    },
    {
      "itemId": "T3_POTION_STONESKIN@3",
      "tier": 3,
      "prices": {
        "Fort Sterling": 39994,
        "Brecilien": 39999
      },
      "sold": 3
    },
    {
      "itemId": "T3_POTION_SLOWFIELD@1",
      "tier": 3,
      "prices": {
        "Lymhurst": 7998,
        "Fort Sterling": 4994,
        "Caerleon": 6000,
        "Brecilien": 3379
      },
      "sold": 51
    },
    {
      "itemId": "T3_POTION_SLOWFIELD@2",
      "tier": 3,
      "prices": {
        "Lymhurst": 10996,
        "Fort Sterling": 11000,
        "Brecilien": 14949
      },
      "sold": 2
    },
    {
      "itemId": "T3_POTION_SLOWFIELD@3",
      "tier": 3,
      "prices": {}
    },
    {
      "itemId": "T4_POTION_ENERGY@1",
      "tier": 4,
      "prices": {
        "Lymhurst": 15000,
        "Fort Sterling": 30999,
        "Brecilien": 39948
      },
      "sold": 18
    },
    {
      "itemId": "T4_POTION_ENERGY@2",
      "tier": 4,
      "prices": {}
    },
    {
      "itemId": "T4_POTION_ENERGY@3",
      "tier": 4,
      "prices": {}
    },
    {
      "itemId": "T4_POTION_HEAL@1",
      "tier": 4,
      "prices": {
        "Lymhurst": 13997,
        "Fort Sterling": 14493,
        "Brecilien": 15027
      },
      "sold": 55
    },
    {
      "itemId": "T4_POTION_HEAL@2",
      "tier": 4,
      "prices": {
        "Fort Sterling": 22999,
        "Thetford": 27998
      },
      "sold": 6
    },
    {
      "itemId": "T4_POTION_HEAL@3",
      "tier": 4,
      "prices": {}
    },
    {
      "itemId": "T4_POTION_BERSERK@1",
      "tier": 4,
      "prices": {
        "Fort Sterling": 9000,
        "Brecilien": 6994
      },
      "sold": 6
    },
    {
      "itemId": "T4_POTION_BERSERK@2",
      "tier": 4,
      "prices": {
        "Brecilien": 9997
      },
      "sold": 5
    },
    {
      "itemId": "T4_POTION_BERSERK@3",
      "tier": 4,
      "prices": {
        "Lymhurst": 34998,
        "Fort Sterling": 39799
      }
    },
    {
      "itemId": "T4_POTION_GATHER@1",
      "tier": 4,
      "prices": {
        "Lymhurst": 7972,
        "Fort Sterling": 6466,
        "Brecilien": 5946
      },
      "sold": 25
    },
    {
      "itemId": "T4_POTION_GATHER@2",
      "tier": 4,
      "prices": {
        "Lymhurst": 25042,
        "Fort Sterling": 20452,
        "Caerleon": 23000,
        "Brecilien": 13984
      },
      "sold": 9
    },
    {
      "itemId": "T4_POTION_GATHER@3",
      "tier": 4,
      "prices": {
        "Lymhurst": 44964,
        "Fort Sterling": 49997,
        "Caerleon": 49994
      },
      "sold": 6
    },
    {
      "itemId": "T4_POTION_LAVA@1",
      "tier": 4,
      "prices": {
        "Lymhurst": 17530,
        "Fort Sterling": 11786,
        "Caerleon": 6522,
        "Brecilien": 10886
      },
      "sold": 18
    },
    {
      "itemId": "T4_POTION_LAVA@2",
      "tier": 4,
      "prices": {
        "Lymhurst": 19988,
        "Caerleon": 25000
      },
      "sold": 14
    },
    {
      "itemId": "T4_POTION_LAVA@3",
      "tier": 4,
      "prices": {
        "Lymhurst": 34998,
        "Fort Sterling": 49999,
        "Caerleon": 45000
      }
    },
    {
      "itemId": "T4_POTION_COOLDOWN@1",
      "tier": 4,
      "prices": {
        "Lymhurst": 3698,
        "Fort Sterling": 3996,
        "Brecilien": 2469
      },
      "sold": 971
    },
    {
      "itemId": "T4_POTION_COOLDOWN@2",
      "tier": 4,
      "prices": {
        "Lymhurst": 19800,
        "Fort Sterling": 15000,
        "Caerleon": 28763,
        "Brecilien": 12993
      },
      "sold": 64
    },
    {
      "itemId": "T4_POTION_COOLDOWN@3",
      "tier": 4,
      "prices": {
        "Lymhurst": 31488,
        "Fort Sterling": 38762,
        "Caerleon": 25497,
        "Brecilien": 29949
      },
      "sold": 13
    },
    {
      "itemId": "T4_POTION_TORNADO@1",
      "tier": 4,
      "prices": {
        "Lymhurst": 10192,
        "Fort Sterling": 7993,
        "Thetford": 4999,
        "Brecilien": 12000
      },
      "sold": 4
    },
    {
      "itemId": "T4_POTION_TORNADO@2",
      "tier": 4,
      "prices": {
        "Lymhurst": 19990
      },
      "sold": 10
    },
    {
      "itemId": "T4_POTION_TORNADO@3",
      "tier": 4,
      "prices": {}
    },
    {
      "itemId": "T5_POTION_ACID@1",
      "tier": 5,
      "prices": {
        "Lymhurst": 17951,
        "Fort Sterling": 19986,
        "Brecilien": 18080
      },
      "sold": 154
    },
    {
      "itemId": "T5_POTION_ACID@2",
      "tier": 5,
      "prices": {
        "Lymhurst": 80000,
        "Fort Sterling": 102969,
        "Brecilien": 68974
      },
      "sold": 8
    },
    {
      "itemId": "T5_POTION_ACID@3",
      "tier": 5,
      "prices": {
        "Lymhurst": 65000
      }
    },
    {
      "itemId": "T5_POTION_MOB_RESET@1",
      "tier": 5,
      "prices": {
        "Lymhurst": 37950,
        "Fort Sterling": 45570,
        "Brecilien": 27988
      },
      "sold": 422
    },
    {
      "itemId": "T5_POTION_MOB_RESET@2",
      "tier": 5,
      "prices": {
        "Lymhurst": 44995,
        "Fort Sterling": 49995,
        "Caerleon": 69999
      },
      "sold": 21
    },
    {
      "itemId": "T5_POTION_MOB_RESET@3",
      "tier": 5,
      "prices": {
        "Fort Sterling": 114889
      },
      "sold": 2
    },
    {
      "itemId": "T5_POTION_CLEANSE2@1",
      "tier": 5,
      "prices": {
        "Lymhurst": 27000,
        "Brecilien": 38996
      },
      "sold": 19
    },
    {
      "itemId": "T5_POTION_CLEANSE2@2",
      "tier": 5,
      "prices": {
        "Brecilien": 20000
      }
    },
    {
      "itemId": "T5_POTION_CLEANSE2@3",
      "tier": 5,
      "prices": {}
    },
    {
      "itemId": "T5_POTION_REVIVE@1",
      "tier": 5,
      "prices": {
        "Lymhurst": 25463,
        "Martlock": 21199,
        "Fort Sterling": 24977,
        "Caerleon": 21977,
        "Brecilien": 14480
      },
      "sold": 61
    },
    {
      "itemId": "T5_POTION_REVIVE@2",
      "tier": 5,
      "prices": {
        "Lymhurst": 29999,
        "Fort Sterling": 33997,
        "Brecilien": 34990
      },
      "sold": 14
    },
    {
      "itemId": "T5_POTION_REVIVE@3",
      "tier": 5,
      "prices": {
        "Lymhurst": 79999,
        "Fort Sterling": 89999
      },
      "sold": 4
    },
    {
      "itemId": "T5_POTION_STONESKIN@1",
      "tier": 5,
      "prices": {
        "Lymhurst": 11991,
        "Fort Sterling": 10974,
        "Caerleon": 9984,
        "Brecilien": 11078
      },
      "sold": 66
    },
    {
      "itemId": "T5_POTION_STONESKIN@2",
      "tier": 5,
      "prices": {
        "Lymhurst": 41994,
        "Brecilien": 28973
      },
      "sold": 5
    },
    {
      "itemId": "T5_POTION_STONESKIN@3",
      "tier": 5,
      "prices": {
        "Lymhurst": 750000
      }
    },
    {
      "itemId": "T5_POTION_SLOWFIELD@1",
      "tier": 5,
      "prices": {
        "Lymhurst": 21995,
        "Fort Sterling": 44331
      },
      "sold": 4
    },
    {
      "itemId": "T5_POTION_SLOWFIELD@2",
      "tier": 5,
      "prices": {
        "Lymhurst": 32499
      }
    },
    {
      "itemId": "T5_POTION_SLOWFIELD@3",
      "tier": 5,
      "prices": {}
    },
    {
      "itemId": "T6_POTION_BERSERK@1",
      "tier": 6,
      "prices": {
        "Lymhurst": 25000,
        "Fort Sterling": 28544,
        "Caerleon": 25555,
        "Brecilien": 25496
      },
      "sold": 1
    },
    {
      "itemId": "T6_POTION_BERSERK@2",
      "tier": 6,
      "prices": {
        "Brecilien": 32000
      },
      "sold": 6
    },
    {
      "itemId": "T6_POTION_BERSERK@3",
      "tier": 6,
      "prices": {}
    },
    {
      "itemId": "T6_POTION_GATHER@1",
      "tier": 6,
      "prices": {
        "Lymhurst": 22558,
        "Fort Sterling": 21588,
        "Thetford": 25567,
        "Brecilien": 20977
      },
      "sold": 74
    },
    {
      "itemId": "T6_POTION_GATHER@2",
      "tier": 6,
      "prices": {
        "Lymhurst": 42977,
        "Fort Sterling": 49962,
        "Caerleon": 40000,
        "Brecilien": 39988
      },
      "sold": 7
    },
    {
      "itemId": "T6_POTION_GATHER@3",
      "tier": 6,
      "prices": {
        "Lymhurst": 94964,
        "Fort Sterling": 70000
      },
      "sold": 1
    },
    {
      "itemId": "T6_POTION_LAVA@1",
      "tier": 6,
      "prices": {
        "Lymhurst": 17996,
        "Fort Sterling": 17975,
        "Thetford": 15488,
        "Caerleon": 23939,
        "Brecilien": 16926
      },
      "sold": 260
    },
    {
      "itemId": "T6_POTION_LAVA@2",
      "tier": 6,
      "prices": {
        "Lymhurst": 26993,
        "Martlock": 25854,
        "Fort Sterling": 24992,
        "Caerleon": 22997,
        "Brecilien": 80966
      },
      "sold": 103
    },
    {
      "itemId": "T6_POTION_LAVA@3",
      "tier": 6,
      "prices": {
        "Fort Sterling": 39999
      }
    },
    {
      "itemId": "T6_POTION_ENERGY@1",
      "tier": 6,
      "prices": {
        "Lymhurst": 29993,
        "Fort Sterling": 38584,
        "Caerleon": 44998,
        "Brecilien": 35482
      },
      "sold": 48
    },
    {
      "itemId": "T6_POTION_ENERGY@2",
      "tier": 6,
      "prices": {
        "Lymhurst": 50000,
        "Fort Sterling": 65000,
        "Brecilien": 62968
      },
      "sold": 14
    },
    {
      "itemId": "T6_POTION_ENERGY@3",
      "tier": 6,
      "prices": {
        "Brecilien": 159977
      },
      "sold": 5
    },
    {
      "itemId": "T6_POTION_HEAL@1",
      "tier": 6,
      "prices": {
        "Lymhurst": 26343,
        "Fort Sterling": 32859,
        "Thetford": 26852,
        "Caerleon": 43483,
        "Brecilien": 25905
      },
      "sold": 5102
    },
    {
      "itemId": "T6_POTION_HEAL@2",
      "tier": 6,
      "prices": {
        "Lymhurst": 60779,
        "Fort Sterling": 59971,
        "Thetford": 60490,
        "Caerleon": 79998,
        "Brecilien": 57608
      },
      "sold": 1386
    },
    {
      "itemId": "T6_POTION_HEAL@3",
      "tier": 6,
      "prices": {
        "Lymhurst": 149995,
        "Fort Sterling": 149961,
        "Caerleon": 175000,
        "Brecilien": 139997
      },
      "sold": 216
    },
    {
      "itemId": "T6_POTION_COOLDOWN@1",
      "tier": 6,
      "prices": {
        "Lymhurst": 16898,
        "Fort Sterling": 19773,
        "Caerleon": 24948,
        "Brecilien": 21999
      },
      "sold": 107
    },
    {
      "itemId": "T6_POTION_COOLDOWN@2",
      "tier": 6,
      "prices": {
        "Fort Sterling": 58990,
        "Brecilien": 45999
      },
      "sold": 7
    },
    {
      "itemId": "T6_POTION_COOLDOWN@3",
      "tier": 6,
      "prices": {
        "Lymhurst": 80000,
        "Fort Sterling": 70000
      }
    },
    {
      "itemId": "T6_ALCOHOL@1",
      "tier": 6,
      "prices": {}
    },
    {
      "itemId": "T6_ALCOHOL@2",
      "tier": 6,
      "prices": {}
    },
    {
      "itemId": "T6_ALCOHOL@3",
      "tier": 6,
      "prices": {}
    },
    {
      "itemId": "T6_POTION_TORNADO@1",
      "tier": 6,
      "prices": {
        "Caerleon": 39999
      },
      "sold": 2
    },
    {
      "itemId": "T6_POTION_TORNADO@2",
      "tier": 6,
      "prices": {
        "Lymhurst": 64999
      }
    },
    {
      "itemId": "T6_POTION_TORNADO@3",
      "tier": 6,
      "prices": {}
    },
    {
      "itemId": "T7_ALCOHOL@1",
      "tier": 7,
      "prices": {}
    },
    {
      "itemId": "T7_ALCOHOL@2",
      "tier": 7,
      "prices": {}
    },
    {
      "itemId": "T7_ALCOHOL@3",
      "tier": 7,
      "prices": {}
    },
    {
      "itemId": "T7_POTION_ACID@1",
      "tier": 7,
      "prices": {
        "Lymhurst": 44944,
        "Fort Sterling": 44991,
        "Caerleon": 49999,
        "Brecilien": 48833
      },
      "sold": 65
    },
    {
      "itemId": "T7_POTION_ACID@2",
      "tier": 7,
      "prices": {
        "Lymhurst": 84872,
        "Martlock": 65000,
        "Fort Sterling": 69977,
        "Caerleon": 500000,
        "Brecilien": 76966
      },
      "sold": 43
    },
    {
      "itemId": "T7_POTION_ACID@3",
      "tier": 7,
      "prices": {
        "Lymhurst": 169911,
        "Fort Sterling": 174884,
        "Brecilien": 164919
      },
      "sold": 64
    },
    {
      "itemId": "T7_POTION_MOB_RESET@1",
      "tier": 7,
      "prices": {
        "Lymhurst": 69961,
        "Fort Sterling": 69996,
        "Caerleon": 75000,
        "Brecilien": 62998
      },
      "sold": 8
    },
    {
      "itemId": "T7_POTION_MOB_RESET@2",
      "tier": 7,
      "prices": {
        "Caerleon": 100000
      },
      "sold": 5
    },
    {
      "itemId": "T7_POTION_MOB_RESET@3",
      "tier": 7,
      "prices": {
        "Lymhurst": 199999,
        "Brecilien": 199998
      }
    },
    {
      "itemId": "T7_POTION_CLEANSE2@1",
      "tier": 7,
      "prices": {
        "Lymhurst": 119998,
        "Fort Sterling": 150000,
        "Brecilien": 104999
      },
      "sold": 6
    },
    {
      "itemId": "T7_POTION_CLEANSE2@2",
      "tier": 7,
      "prices": {
        "Lymhurst": 200000,
        "Fort Sterling": 199996
      },
      "sold": 1
    },
    {
      "itemId": "T7_POTION_CLEANSE2@3",
      "tier": 7,
      "prices": {
        "Lymhurst": 130000,
        "Brecilien": 249988
      }
    },
    {
      "itemId": "T7_POTION_REVIVE@1",
      "tier": 7,
      "prices": {
        "Lymhurst": 26738,
        "Martlock": 26000,
        "Fort Sterling": 26978,
        "Thetford": 27775,
        "Caerleon": 60995,
        "Brecilien": 26208
      },
      "sold": 2431
    },
    {
      "itemId": "T7_POTION_REVIVE@2",
      "tier": 7,
      "prices": {
        "Lymhurst": 59886,
        "Martlock": 61961,
        "Fort Sterling": 64915,
        "Thetford": 61531,
        "Caerleon": 60094,
        "Brecilien": 60021
      },
      "sold": 485
    },
    {
      "itemId": "T7_POTION_REVIVE@3",
      "tier": 7,
      "prices": {
        "Lymhurst": 149996,
        "Fort Sterling": 128988,
        "Caerleon": 169999,
        "Brecilien": 153999
      },
      "sold": 48
    },
    {
      "itemId": "T7_POTION_STONESKIN@1",
      "tier": 7,
      "prices": {
        "Lymhurst": 30939,
        "Martlock": 35575,
        "Fort Sterling": 33438,
        "Caerleon": 43000,
        "Brecilien": 39998
      },
      "sold": 630
    },
    {
      "itemId": "T7_POTION_STONESKIN@2",
      "tier": 7,
      "prices": {
        "Lymhurst": 66880,
        "Fort Sterling": 63496,
        "Caerleon": 81999,
        "Brecilien": 65997
      },
      "sold": 86
    },
    {
      "itemId": "T7_POTION_STONESKIN@3",
      "tier": 7,
      "prices": {
        "Lymhurst": 249894,
        "Fort Sterling": 184993,
        "Caerleon": 184999,
        "Brecilien": 249960
      },
      "sold": 11
    },
    {
      "itemId": "T7_POTION_SLOWFIELD@1",
      "tier": 7,
      "prices": {
        "Lymhurst": 39999,
        "Fort Sterling": 50051,
        "Caerleon": 70000,
        "Brecilien": 65000
      },
      "sold": 6
    },
    {
      "itemId": "T7_POTION_SLOWFIELD@2",
      "tier": 7,
      "prices": {},
      "sold": 8
    },
    {
      "itemId": "T7_POTION_SLOWFIELD@3",
      "tier": 7,
      "prices": {}
    },
    {
      "itemId": "T8_POTION_CLEANSE@1",
      "tier": 8,
      "prices": {
        "Lymhurst": 44830,
        "Fort Sterling": 33897,
        "Thetford": 44917,
        "Caerleon": 44855,
        "Brecilien": 32974
      },
      "sold": 112
    },
    {
      "itemId": "T8_POTION_CLEANSE@2",
      "tier": 8,
      "prices": {
        "Lymhurst": 92974,
        "Fort Sterling": 118995,
        "Caerleon": 159998,
        "Brecilien": 134988
      },
      "sold": 18
    },
    {
      "itemId": "T8_POTION_CLEANSE@3",
      "tier": 8,
      "prices": {
        "Lymhurst": 205999,
        "Martlock": 269995,
        "Fort Sterling": 207497,
        "Caerleon": 248974,
        "Brecilien": 249999
      },
      "sold": 4
    },
    {
      "itemId": "T8_POTION_BERSERK@1",
      "tier": 8,
      "prices": {
        "Lymhurst": 109999,
        "Fort Sterling": 89963,
        "Caerleon": 84852,
        "Brecilien": 79999
      },
      "sold": 5
    },
    {
      "itemId": "T8_POTION_BERSERK@2",
      "tier": 8,
      "prices": {
        "Lymhurst": 147999,
        "Fort Sterling": 259889,
        "Caerleon": 159999
      },
      "sold": 1
    },
    {
      "itemId": "T8_POTION_BERSERK@3",
      "tier": 8,
      "prices": {
        "Lymhurst": 189944,
        "Fort Sterling": 174999,
        "Caerleon": 183000,
        "Brecilien": 249939
      },
      "sold": 19
    },
    {
      "itemId": "T8_POTION_GATHER@1",
      "tier": 8,
      "prices": {
        "Lymhurst": 49775,
        "Fort Sterling": 39984,
        "Caerleon": 44998,
        "Brecilien": 45880
      },
      "sold": 186
    },
    {
      "itemId": "T8_POTION_GATHER@2",
      "tier": 8,
      "prices": {
        "Lymhurst": 71985,
        "Fort Sterling": 63831,
        "Caerleon": 178973,
        "Brecilien": 74490
      },
      "sold": 73
    },
    {
      "itemId": "T8_POTION_GATHER@3",
      "tier": 8,
      "prices": {
        "Lymhurst": 161220,
        "Martlock": 159860,
        "Fort Sterling": 153259,
        "Thetford": 161972,
        "Bridgewatch": 178962,
        "Caerleon": 199985,
        "Brecilien": 145540
      },
      "sold": 143
    },
    {
      "itemId": "T8_POTION_LAVA@1",
      "tier": 8,
      "prices": {
        "Lymhurst": 44678,
        "Fort Sterling": 53998,
        "Thetford": 44888,
        "Caerleon": 59995,
        "Brecilien": 49993
      },
      "sold": 238
    },
    {
      "itemId": "T8_POTION_LAVA@2",
      "tier": 8,
      "prices": {
        "Lymhurst": 78534,
        "Fort Sterling": 84999,
        "Caerleon": 88994,
        "Brecilien": 84973
      },
      "sold": 83
    },
    {
      "itemId": "T8_POTION_LAVA@3",
      "tier": 8,
      "prices": {
        "Lymhurst": 199000,
        "Fort Sterling": 119996,
        "Thetford": 157487,
        "Caerleon": 174999,
        "Brecilien": 198999
      },
      "sold": 11
    },
    {
      "itemId": "T8_POTION_COOLDOWN@1",
      "tier": 8,
      "prices": {
        "Lymhurst": 30995,
        "Martlock": 29982,
        "Fort Sterling": 32950,
        "Caerleon": 42098,
        "Brecilien": 36879
      },
      "sold": 1261
    },
    {
      "itemId": "T8_POTION_COOLDOWN@2",
      "tier": 8,
      "prices": {
        "Lymhurst": 66933,
        "Martlock": 69946,
        "Fort Sterling": 64767,
        "Caerleon": 159924,
        "Brecilien": 60731
      },
      "sold": 115
    },
    {
      "itemId": "T8_POTION_COOLDOWN@3",
      "tier": 8,
      "prices": {
        "Lymhurst": 214890,
        "Fort Sterling": 198975,
        "Caerleon": 199999,
        "Brecilien": 224963
      },
      "sold": 30
    },
    {
      "itemId": "T8_POTION_TORNADO@1",
      "tier": 8,
      "prices": {
        "Lymhurst": 45000,
        "Fort Sterling": 45000,
        "Brecilien": 58999
      },
      "sold": 3
    },
    {
      "itemId": "T8_POTION_TORNADO@2",
      "tier": 8,
      "prices": {
        "Caerleon": 100000
      },
      "sold": 2
    },
    {
      "itemId": "T8_POTION_TORNADO@3",
      "tier": 8,
      "prices": {}
    },
    {
      "itemId": "T8_ALCOHOL@1",
      "tier": 8,
      "prices": {}
    },
    {
      "itemId": "T8_ALCOHOL@2",
      "tier": 8,
      "prices": {}
    },
    {
      "itemId": "T8_ALCOHOL@3",
      "tier": 8,
      "prices": {}
    }
  ]
}